Workbook

Sheet Main
A1: Ship_Name | B1: Notes | C1: Ship_Notes | D1: First_Name | E1: Surname | F1: Birthdate | G1: ID | H1: Ref_Page | I1: Book | J1: Commander | K1: Father_FirstName | L1: Father_Surname | M1: Mother_FirstName | N1: Mother_Surname | O1: Gender | P1: Race | Q1: Ethnicity | R1: Origination_Port | S1: Origination_State | T1: Departure_Port | U1: Departure_Date | V1: Arrival_Port_City | W1: Primary_Source_1 | X1: Primary_Source_2 | Y1: Enslaver | Z1: Origin | AA1: Extracted_City | AB1: Extracted_County | AC1: Extracted_State | AD1: Country | AE1: State | AF1: County | AG1: Departure_Coordinates
A2: 3 Friends | B2: William Johnson, 21, stout likely fellow, (Lt. Richard Holland). Formerly slave to John Chapman of Princess Ann County, Virginia; left him 4 years. | C2: Sloop 3 Friends bound for River St. John's John Stewart, Master | D2: William | E2: Johnson | F2: 1762 | G2: 744 | H2: - | I2: Book One Part One | J2: John Stewart | K2: - | L2: - | M2: - | N2: - | O2: Male | P2: Black | Q2: African American | R2: Formerly slave to John Chapman of Princess Ann County | S2: Virginia | T2: - | U2: - | V2: River St. John's | W2: - | X2: - | Y2: Lt. Richard Holland | Z2: Black | AA2: - | AB2: - | AC2: Virginia | AD2: United States | AG2: =IF(AD2="United States", IFERROR(INDEX(Sheet2!$C:$C, MATCH(AE2&AF2, Sheet2!$E:$E, 0)) & ", " & INDEX(Sheet2!$D:$D, MATCH(AE2&AF2, Sheet2!$E:$E, 0)), ""), "-")
A3: 3 Friends | B3: Sally her child, 8 mo. | C3: Sloop 3 Friends bound for River St. John's John Stewart, Master | D3: Sally | E3: her child | F3: 1775 | G3: 746 | H3: - | I3: Book One Part One | J3: John Stewart | K3: - | L3: - | M3: Elizabeth | N3: Merrick | O3: Child Male | P3: Black | Q3: African American | R3: - | S3: - | T3: - | U3: - | V3: River St. John's | W3: - | X3: - | Y3: - | Z3: Black | AA3: - | AB3: - | AC3: mo | AD3: United States | AG3: =IF(AD3="United States", IFERROR(INDEX(Sheet2!$C:$C, MATCH(AE3&AF3, Sheet2!$E:$E, 0)) & ", " & INDEX(Sheet2!$D:$D, MATCH(AE3&AF3, Sheet2!$E:$E, 0)), ""), "-")
A4: 3 Friends | B4: Elizabeth Merrick, 27, stout wench, M, (Luther Hatheway). Born free; served her time with Lambert Woodward of Newtown, Long Island. | C4: Sloop 3 Friends bound for River St. John's John Stewart, Master | D4: Elizabeth | E4: Merrick | F4: 1756 | G4: 743 | H4: - | I4: Book One Part One | J4: John Stewart | K4: - | L4: - | M4: - | N4: - | O4: Female | P4: Black | Q4: African American | R4: - | S4: - | T4: - | U4: - | V4: River St. John's | W4: - | X4: - | Y4: Luther Hatheway | Z4: Black | AA4: Newtown | AB4: - | AC4: Long Island | AD4: United States | AG4: =IF(AD4="United States", IFERROR(INDEX(Sheet2!$C:$C, MATCH(AE4&AF4, Sheet2!$E:$E, 0)) & ", " & INDEX(Sheet2!$D:$D, MATCH(AE4&AF4, Sheet2!$E:$E, 0)), ""), "-")
A5: 3 Friends | B5: Richard Merrick, 32, stout likely fellow, (Sam Wilson). Formerly slave to Samuel Merrick of Springfield, Massachusetts, who gave him his freedom & produced a Certificate dated 4 November 74, signed by Merrick, Philips & Dr. White. | C5: Sloop 3 Friends bound for River St. John's John Stewart, Master | D5: Richard | E5: Merrick | F5: 1751 | G5: 742 | H5: - | I5: Book One Part One | J5: John Stewart | K5: Tom | L5: Gunn | M5: - | N5: - | O5: Male | P5: Black | Q5: African American | R5: - | S5: - | T5: - | U5: - | V5: River St. John's | W5: - | X5: - | Y5: Sam Wilson | Z5: Black | AA5: Springfield | AB5: - | AC5: Massachusetts | AD5: United States | AG5: =IF(AD5="United States", IFERROR(INDEX(Sheet2!$C:$C, MATCH(AE5&AF5, Sheet2!$E:$E, 0)) & ", " & INDEX(Sheet2!$D:$D, MATCH(AE5&AF5, Sheet2!$E:$E, 0)), ""), "-")
A6: 3 Friends | B6: Tom Gunn, 43, stout, pockmarked, (Sam Wilson). Formerly slave to Enos Gunn of Waterbury, Connecticut. | C6: Sloop 3 Friends bound for River St. John's John Stewart, Master | D6: Tom | E6: Gunn | F6: 1740 | G6: 741 | H6: - | I6: Book One Part One | J6: John Stewart | K6: - | L6: - | M6: - | N6: - | O6: Male | P6: Black | Q6: African American | R6: - | S6: - | T6: - | U6: - | V6: River St. John's | W6: - | X6: - | Y6: Sam Wilson | Z6: Black | AA6: Waterbury | AB6: - | AC6: Connecticut | AD6: United States | AG6: =IF(AD6="United States", IFERROR(INDEX(Sheet2!$C:$C, MATCH(AE6&AF6, Sheet2!$E:$E, 0)) & ", " & INDEX(Sheet2!$D:$D, MATCH(AE6&AF6, Sheet2!$E:$E, 0)), ""), "-")
A7: 3 Friends | B7: Hannah and, 16, stout wench, (Lt. Richard Holland). Born free in Cow Neck, Long Island, lived with Caleb Merrill till within this last year. | C7: Sloop 3 Friends bound for River St. John's John Stewart, Master | D7: Hannah | E7: and | F7: 1767 | G7: 745 | H7: - | I7: Book One Part One | J7: John Stewart | K7: - | L7: - | M7: - | N7: - | O7: Child Female | P7: Black | Q7: African American | R7: - | S7: - | T7: - | U7: - | V7: River St. John's | W7: - | X7: - | Y7: Lt. Richard Holland | Z7: Black | AA7: - | AB7: - | AC7: Long Island | AD7: United States | AG7: =IF(AD7="United States", IFERROR(INDEX(Sheet2!$C:$C, MATCH(AE7&AF7, Sheet2!$E:$E, 0)) & ", " & INDEX(Sheet2!$D:$D, MATCH(AE7&AF7, Sheet2!$E:$E, 0)), ""), "-")
A8: 3 Sisters | B8: 18 September | C8: 3 Sisters bound for Quebec John Wardell | D8: 18 | E8: September | F8: 1765 | G8: 2716 | I8: Book One Part Two | J8: - | O8: Male | P8: Black | Q8: African American | V8: Quebec John Wardell | Y8: - | Z8: Black | AA8: - | AB8: - | AC8: - | AD8: United States | AG8: =IF(AD8="United States", IFERROR(INDEX(Sheet2!$C:$C, MATCH(AE8&AF8, Sheet2!$E:$E, 0)) & ", " & INDEX(Sheet2!$D:$D, MATCH(AE8&AF8, Sheet2!$E:$E, 0)), ""), "-")
A9: Alexander | B9: Cairo, 20, stout wench, (James Peters). Property of James Petes. | C9: Alexander bound for St. John's Roger Alderson | D9: Cairo | E9: - | F9: 1763 | G9: 2254 | H9: 70 | I9: Book Two | J9: Roger Alderson | K9: - | L9: - | M9: - | N9: - | O9: Female | P9: Black | Q9: African American | R9: New York | S9: - | T9: New York | U9: Fall 1783 | V9: St. John's | W9: Book of Negroes, British Headquarters Papers PRO 30/55/100; Loyalist evacuation shipping lists (1782–1784) | X9: Loyalist evacuation lists | Y9: James Peters | Z9: Black | AA9: - | AB9: - | AC9: Cairo | AD9: United States | AG9: =IF(AD9="United States", IFERROR(INDEX(Sheet2!$C:$C, MATCH(AE9&AF9, Sheet2!$E:$E, 0)) & ", " & INDEX(Sheet2!$D:$D, MATCH(AE9&AF9, Sheet2!$E:$E, 0)), ""), "-")
A10: Alexander | B10: Bella, 14, stout wench, (James Peters). Property of James Peters. | C10: Alexander bound for St. John's Roger Alderson | D10: Bella | E10: - | F10: 1769 | G10: 2255 | H10: 70 | I10: Book Two | J10: Roger Alderson | K10: - | L10: - | M10: - | N10: - | O10: Child Female | P10: Black | Q10: African American | R10: New York | S10: - | T10: New York | U10: Fall 1783 | V10: St. John's | W10: Book of Negroes, British Headquarters Papers PRO 30/55/100; Loyalist evacuation shipping lists (1782–1784) | X10: Loyalist evacuation lists | Y10: James Peters | Z10: Black | AA10: - | AB10: - | AC10: - | AD10: United States | AG10: =IF(AD10="United States", IFERROR(INDEX(Sheet2!$C:$C, MATCH(AE10&AF10, Sheet2!$E:$E, 0)) & ", " & INDEX(Sheet2!$D:$D, MATCH(AE10&AF10, Sheet2!$E:$E, 0)), ""), "-")
A11: Alexander | B11: Esther, 18, stout wench, M, (Bartholomew Cranell). Property of Bartholomew Crannell. | C11: Alexander bound for St. John's Roger Alderson | D11: Esther | E11: - | F11: 1765 | G11: 2256 | H11: 70 | I11: Book Two | J11: Roger Alderson | K11: - | L11: - | M11: - | N11: - | O11: Female | P11: Black | Q11: African American | R11: New York | S11: - | T11: New York | U11: Fall 1783 | V11: St. John's | W11: Book of Negroes, British Headquarters Papers PRO 30/55/100; Loyalist evacuation shipping lists (1782–1784) | X11: Loyalist evacuation lists | Y11: Bartholomew Cranell | Z11: Black | AA11: - | AB11: - | AC11: - | AD11: United States | AG11: =IF(AD11="United States", IFERROR(INDEX(Sheet2!$C:$C, MATCH(AE11&AF11, Sheet2!$E:$E, 0)) & ", " & INDEX(Sheet2!$D:$D, MATCH(AE11&AF11, Sheet2!$E:$E, 0)), ""), "-")
A12: Alexander | B12: Robert, 36, stout fellow, (Bartholomew Crannell). Formerly slave to Isaac Conklin, 9 Partners; left him 2 years ago. | C12: Alexander bound for St. John's Roger Alderson | D12: Robert | E12: - | F12: 1747 | G12: 2258 | H12: 70 | I12: Book Two | J12: Roger Alderson | K12: - | L12: - | M12: - | N12: - | O12: Male | P12: Black | Q12: African American | R12: New York | S12: - | T12: New York | U12: Fall 1783 | V12: St. John's | W12: Book of Negroes, British Headquarters Papers PRO 30/55/100; Loyalist evacuation shipping lists (1782–1784) | X12: Loyalist evacuation lists | Y12: Bartholomew Crannell | Z12: Black | AA12: - | AB12: - | AC12: - | AD12: United States | AG12: =IF(AD12="United States", IFERROR(INDEX(Sheet2!$C:$C, MATCH(AE12&AF12, Sheet2!$E:$E, 0)) & ", " & INDEX(Sheet2!$D:$D, MATCH(AE12&AF12, Sheet2!$E:$E, 0)), ""), "-")
A13: Alexander | B13: Pompey, 25, stout fellow, on his own bottom. Born free. | C13: Alexander bound for St. John's Roger Alderson | D13: Pompey | E13: - | F13: 1758 | G13: 2259 | H13: 70 | I13: Book Two | J13: Roger Alderson | K13: - | L13: - | M13: - | N13: - | O13: Male | P13: Black | Q13: African American | R13: New York | S13: - | T13: New York | U13: Fall 1783 | V13: St. John's | W13: Book of Negroes, British Headquarters Papers PRO 30/55/100; Loyalist evacuation shipping lists (1782–1784) | X13: Loyalist evacuation lists | Y13: - | Z13: Black | AA13: - | AB13: - | AC13: Pompey | AD13: United States | AG13: =IF(AD13="United States", IFERROR(INDEX(Sheet2!$C:$C, MATCH(AE13&AF13, Sheet2!$E:$E, 0)) & ", " & INDEX(Sheet2!$D:$D, MATCH(AE13&AF13, Sheet2!$E:$E, 0)), ""), "-")
A14: Alexander | B14: Sam, 35, (Bartholomew Cranell). Property of Bartholomew Crannell. | C14: Alexander bound for St. John's Roger Alderson | D14: Sam | E14: - | F14: 1748 | G14: 2257 | H14: 70 | I14: Book Two | J14: Roger Alderson | K14: - | L14: - | M14: - | N14: - | O14: Male | P14: Black | Q14: African American | R14: New York | S14: - | T14: New York | U14: Fall 1783 | V14: St. John's | W14: Book of Negroes, British Headquarters Papers PRO 30/55/100; Loyalist evacuation shipping lists (1782–1784) | X14: Loyalist evacuation lists | Y14: Bartholomew Cranell | Z14: Black | AA14: - | AB14: - | AC14: - | AD14: United States | AG14: =IF(AD14="United States", IFERROR(INDEX(Sheet2!$C:$C, MATCH(AE14&AF14, Sheet2!$E:$E, 0)) & ", " & INDEX(Sheet2!$D:$D, MATCH(AE14&AF14, Sheet2!$E:$E, 0)), ""), "-")
A15: Amities Production | D15: Job | E15: State | F15: 1759 | G15: 742 | H15: 35 | J15: Thomas Reid | O15: Male | R15: New York | T15: New York | U15: 16 Jun 1783 | V15: St. Johns | W15: Book of Negroes, British Headquarters Papers PRO 30/55/100; Loyalist evacuation shipping lists (1782–1784) | X15: Loyalist evacuation lists | Y15: - | AA15: - | AB15: - | AC15: - | AD15: United States | AG15: =IF(AD15="United States", IFERROR(INDEX(Sheet2!$C:$C, MATCH(AE15&AF15, Sheet2!$E:$E, 0)) & ", " & INDEX(Sheet2!$D:$D, MATCH(AE15&AF15, Sheet2!$E:$E, 0)), ""), "-")
A16: Amities Production | D16: William | E16: Holchapan | F16: 1743 | G16: 743 | H16: 35 | J16: Thomas Reid | O16: Male | R16: New York | T16: New York | U16: 16 Jun 1783 | V16: St. Johns | W16: Book of Negroes, British Headquarters Papers PRO 30/55/100; Loyalist evacuation shipping lists (1782–1784) | X16: Loyalist evacuation lists | Y16: - | AA16: - | AB16: - | AC16: - | AD16: United States | AG16: =IF(AD16="United States", IFERROR(INDEX(Sheet2!$C:$C, MATCH(AE16&AF16, Sheet2!$E:$E, 0)) & ", " & INDEX(Sheet2!$D:$D, MATCH(AE16&AF16, Sheet2!$E:$E, 0)), ""), "-")
A17: Amities Production | D17: George | E17: State | F17: 1758 | G17: 740 | H17: 35 | J17: Thomas Reid | O17: Male | R17: New York | T17: New York | U17: 16 Jun 1783 | V17: St. Johns | W17: Book of Negroes, British Headquarters Papers PRO 30/55/100; Loyalist evacuation shipping lists (1782–1784) | X17: Loyalist evacuation lists | Y17: - | AA17: - | AB17: - | AC17: - | AD17: United States | AG17: =IF(AD17="United States", IFERROR(INDEX(Sheet2!$C:$C, MATCH(AE17&AF17, Sheet2!$E:$E, 0)) & ", " & INDEX(Sheet2!$D:$D, MATCH(AE17&AF17, Sheet2!$E:$E, 0)), ""), "-")
A18: Amities Production | D18: Mary | E18: State | F18: 1762 | G18: 741 | H18: 35 | J18: Thomas Reid | O18: Female | R18: New York | T18: New York | U18: 16 Jun 1783 | V18: St. Johns | W18: Book of Negroes, British Headquarters Papers PRO 30/55/100; Loyalist evacuation shipping lists (1782–1784) | X18: Loyalist evacuation lists | Y18: - | AA18: - | AB18: - | AC18: - | AD18: United States | AG18: =IF(AD18="United States", IFERROR(INDEX(Sheet2!$C:$C, MATCH(AE18&AF18, Sheet2!$E:$E, 0)) & ", " & INDEX(Sheet2!$D:$D, MATCH(AE18&AF18, Sheet2!$E:$E, 0)), ""), "-")
A19: Amities Production | D19: William | E19: Stepney | F19: 1759 | G19: 739 | H19: 35 | J19: Thomas Reid | O19: Male | R19: New York | T19: New York | U19: 16 Jun 1783 | V19: St. Johns | W19: Book of Negroes, British Headquarters Papers PRO 30/55/100; Loyalist evacuation shipping lists (1782–1784) | X19: Loyalist evacuation lists | Y19: - | AA19: - | AB19: - | AC19: - | AD19: United States | AG19: =IF(AD19="United States", IFERROR(INDEX(Sheet2!$C:$C, MATCH(AE19&AF19, Sheet2!$E:$E, 0)) & ", " & INDEX(Sheet2!$D:$D, MATCH(AE19&AF19, Sheet2!$E:$E, 0)), ""), "-")
A20: Amity's Production | B20: William Holchapan, 40, stout fellow, M, (on his own bottom). Born free and baptized in the year 1779 in the Parish of St. Paul's, London. | C20: Amity's Production bound for St. John's Thomas Reid, Master | D20: William | E20: Holchapan | F20: 1743 | G20: 678 | H20: - | I20: Book One Part One | J20: Thomas Reid | K20: - | L20: - | M20: - | N20: - | O20: Male | P20: Black | Q20: African American | R20: - | S20: - | T20: - | U20: - | V20: St. John's | W20: - | X20: - | Y20: - | Z20: Black | AA20: - | AB20: St | AC20: London | AD20: United States | AG20: =IF(AD20="United States", IFERROR(INDEX(Sheet2!$C:$C, MATCH(AE20&AF20, Sheet2!$E:$E, 0)) & ", " & INDEX(Sheet2!$D:$D, MATCH(AE20&AF20, Sheet2!$E:$E, 0)), ""), "-")
A21: Amity's Production | B21: Job State, 24, stout fellow, M, (on his own bottom). Born free at New York. | C21: Amity's Production bound for St. John's Thomas Reid, Master | D21: Job | E21: State | F21: 1759 | G21: 677 | H21: - | I21: Book One Part One | J21: Thomas Reid | K21: - | L21: - | M21: - | N21: - | O21: Male | P21: Black | Q21: African American | R21: - | S21: New York | T21: - | U21: - | V21: St. John's | W21: - | X21: - | Y21: - | Z21: Black | AA21: - | AB21: - | AC21: New York | AD21: United States | AG21: =IF(AD21="United States", IFERROR(INDEX(Sheet2!$C:$C, MATCH(AE21&AF21, Sheet2!$E:$E, 0)) & ", " & INDEX(Sheet2!$D:$D, MATCH(AE21&AF21, Sheet2!$E:$E, 0)), ""), "-")
A22: Amity's Production | B22: Mary State, 21, half Indian, (on her own bottom). Born free on Long Island. | C22: Amity's Production bound for St. John's Thomas Reid, Master | D22: Mary | E22: State | F22: 1762 | G22: 676 | H22: - | I22: Book One Part One | J22: Thomas Reid | K22: - | L22: - | M22: - | N22: - | O22: Male | P22: Half Indian | Q22: Mixed Race | R22: - | S22: - | T22: - | U22: - | V22: St. John's | W22: - | X22: - | Y22: - | Z22: Mulatto | AA22: - | AB22: - | AC22: Long Island | AD22: United States | AG22: =IF(AD22="United States", IFERROR(INDEX(Sheet2!$C:$C, MATCH(AE22&AF22, Sheet2!$E:$E, 0)) & ", " & INDEX(Sheet2!$D:$D, MATCH(AE22&AF22, Sheet2!$E:$E, 0)), ""), "-")
A23: Amity's Production | B23: George State, 25, stout fellow, M, (on his own bottom). Born free at New York. | C23: Amity's Production bound for St. John's Thomas Reid, Master | D23: George | E23: State | F23: 1758 | G23: 675 | H23: - | I23: Book One Part One | J23: Thomas Reid | K23: - | L23: - | M23: - | N23: - | O23: Male | P23: Black | Q23: African American | R23: - | S23: New York | T23: - | U23: - | V23: St. John's | W23: - | X23: - | Y23: - | Z23: Black | AA23: - | AB23: - | AC23: New York | AD23: United States | AG23: =IF(AD23="United States", IFERROR(INDEX(Sheet2!$C:$C, MATCH(AE23&AF23, Sheet2!$E:$E, 0)) & ", " & INDEX(Sheet2!$D:$D, MATCH(AE23&AF23, Sheet2!$E:$E, 0)), ""), "-")
A24: Amity's Production | B24: William Stepney, 24, stout fellow, B, (on his own bottom). Born free at St. Augustine. | C24: Amity's Production bound for St. John's Thomas Reid, Master | D24: William | E24: Stepney | F24: 1759 | G24: 674 | H24: - | I24: Book One Part One | J24: Thomas Reid | K24: - | L24: - | M24: - | N24: - | O24: Male | P24: Black | Q24: African American | R24: - | S24: - | T24: - | U24: - | V24: St. John's | W24: - | X24: - | Y24: - | Z24: Black | AA24: - | AB24: - | AC24: St. Augustine | AD24: United States | AG24: =IF(AD24="United States", IFERROR(INDEX(Sheet2!$C:$C, MATCH(AE24&AF24, Sheet2!$E:$E, 0)) & ", " & INDEX(Sheet2!$D:$D, MATCH(AE24&AF24, Sheet2!$E:$E, 0)), ""), "-")
A25: Ann | B25: James Robertson, 2½, small boy, (Capt. Mowat). | C25: Ship Ann bound for Port Roseway Joseph Clark, Master | D25: James | E25: Robertson | F25: - | G25: 209 | H25: 22 | I25: Book One Part One | J25: Joseph Clark | K25: - | L25: - | M25: - | N25: - | O25: Child Male | P25: Black | Q25: African American | R25: New York | S25: - | T25: New York | U25: 8 Jul 1783 | V25: Port Roseway | W25: Book of Negroes, British Headquarters Papers PRO 30/55/100; Loyalist evacuation shipping lists (1782–1784) | X25: Loyalist evacuation lists | Y25: Capt. Mowat | Z25: Black | AA25: - | AB25: - | AC25: - | AD25: United States | AG25: =IF(AD25="United States", IFERROR(INDEX(Sheet2!$C:$C, MATCH(AE25&AF25, Sheet2!$E:$E, 0)) & ", " & INDEX(Sheet2!$D:$D, MATCH(AE25&AF25, Sheet2!$E:$E, 0)), ""), "-")
A26: Ann | B26: Betsey Robertson, 46, thin wench, (Capt. Mowat). Formerly slave to Captain Paul Layon, Portsmouth, Virginia; left him with her husband. | C26: Ship Ann bound for Port Roseway Joseph Clark, Master | D26: Betsey | E26: Robertson | F26: 1737 | G26: 208 | H26: 22 | I26: Book One Part One | J26: Joseph Clark | K26: - | L26: - | M26: Barbara | N26: Ogden | O26: Female | P26: Black | Q26: African American | R26: New York | S26: Virginia | T26: New York | U26: Fall 1783 | V26: Port Roseway | W26: Book of Negroes, British Headquarters Papers PRO 30/55/100; Loyalist evacuation shipping lists (1782–1784) | X26: Loyalist evacuation lists | Y26: Capt. Mowat | Z26: Black | AA26: Portsmouth | AB26: - | AC26: Virginia | AD26: United States | AG26: =IF(AD26="United States", IFERROR(INDEX(Sheet2!$C:$C, MATCH(AE26&AF26, Sheet2!$E:$E, 0)) & ", " & INDEX(Sheet2!$D:$D, MATCH(AE26&AF26, Sheet2!$E:$E, 0)), ""), "-")
A27: Ann | B27: James Robertson, 49, thin, pilot by order, (Capt. Mowat). Formerly slave to Captain Paul Layon, Portsmouth, Virginia; left him 4 years ago, employed as a pilot. | C27: Ship Ann bound for Port Roseway Joseph Clark, Master | D27: James | E27: Robertson | F27: 1734 | G27: 207 | H27: 22 | I27: Book One Part One | J27: Joseph Clark | K27: - | L27: - | M27: - | N27: - | O27: Male | P27: Black | Q27: African American | R27: New York | S27: Virginia | T27: New York | U27: 8 Jul 1783 | V27: Port Roseway | W27: Book of Negroes, British Headquarters Papers PRO 30/55/100; Loyalist evacuation shipping lists (1782–1784) | X27: Loyalist evacuation lists | Y27: Capt. Mowat | Z27: Black | AA27: Portsmouth | AB27: - | AC27: Virginia | AD27: United States | AG27: =IF(AD27="United States", IFERROR(INDEX(Sheet2!$C:$C, MATCH(AE27&AF27, Sheet2!$E:$E, 0)) & ", " & INDEX(Sheet2!$D:$D, MATCH(AE27&AF27, Sheet2!$E:$E, 0)), ""), "-")
A28: Ann | B28: William, 14, fine boy. (John Anderson of Port Roseway, claimant.) John Anderson purchased from Hugh Dunn, New York; born nigh Stoney Point. Formerly the property of Edison, taken with a guard of the enemy by a party from the Garrison, 1779. | C28: Ship Ann bound for Port Roseway Joseph Clark, Master | D28: William | E28: - | F28: 1769 | G28: 239 | H28: 22 | I28: Book One Part One | J28: Joseph Clark | K28: - | L28: - | M28: - | N28: - | O28: Child Male | P28: Black | Q28: African American | R28: New York | S28: New York | T28: New York | U28: Fall 1783 | V28: Port Roseway | W28: Book of Negroes, British Headquarters Papers PRO 30/55/100; Loyalist evacuation shipping lists (1782–1784) | X28: Loyalist evacuation lists | Y28: John Anderson of Port Roseway, claimant. | Z28: Black | AA28: New York | AB28: Edison | AC28: Garrison | AD28: United States | AG28: =IF(AD28="United States", IFERROR(INDEX(Sheet2!$C:$C, MATCH(AE28&AF28, Sheet2!$E:$E, 0)) & ", " & INDEX(Sheet2!$D:$D, MATCH(AE28&AF28, Sheet2!$E:$E, 0)), ""), "-")
A29: Ann | B29: Joe Gold, 30, stout black, (Robert Turnbull). Formerly slave to Daniel Descan , about 14 miles from Charlestown, South Carolina; left him 4 years ago. | C29: Ship Ann bound for Port Roseway Joseph Clark, Master | D29: Joe | E29: Gold | F29: 1753 | G29: 240 | H29: 23 | I29: Book One Part One | J29: Joseph Clark | K29: - | L29: - | M29: - | N29: - | O29: Male | P29: Black | Q29: African American | R29: New York | S29: South Carolina | T29: New York | U29: Fall 1783 | V29: Port Roseway | W29: Book of Negroes, British Headquarters Papers PRO 30/55/100; Loyalist evacuation shipping lists (1782–1784) | X29: Loyalist evacuation lists | Y29: Robert Turnbull | Z29: Black | AA29: Charlestown | AB29: - | AC29: South Carolina | AD29: United States | AG29: =IF(AD29="United States", IFERROR(INDEX(Sheet2!$C:$C, MATCH(AE29&AF29, Sheet2!$E:$E, 0)) & ", " & INDEX(Sheet2!$D:$D, MATCH(AE29&AF29, Sheet2!$E:$E, 0)), ""), "-")
A30: Ann | B30: Effie Warner, 33, stout wench & boy 2 yrs, old, (William Hill). Formerly slave to John Matthews, Princess Ann, Virginia; left him 5 years ago. GBC. | C30: Ship Ann bound for Port Roseway Joseph Clark, Master | D30: Effie | E30: Warner | F30: 1750 | G30: 236 | H30: - | I30: Book One Part One | J30: Joseph Clark | K30: - | L30: - | M30: - | N30: - | O30: Child Female | P30: Black | Q30: African American | R30: Princess Ann | S30: Virginia | T30: - | U30: - | V30: Port Roseway | W30: - | X30: - | Y30: William Hill | Z30: Black | AA30: - | AB30: - | AC30: Virginia | AD30: United States | AG30: =IF(AD30="United States", IFERROR(INDEX(Sheet2!$C:$C, MATCH(AE30&AF30, Sheet2!$E:$E, 0)) & ", " & INDEX(Sheet2!$D:$D, MATCH(AE30&AF30, Sheet2!$E:$E, 0)), ""), "-")
A31: Ann | B31: Sukey her daughter, 12, thin mulatto girl, (Robert Turnbull). Formerly slave to Mrs. Harriet Crook, Savannah, Georgia; left that place 5 years ago. | C31: Ship Ann bound for Port Roseway Joseph Clark, Master | D31: Sukey | E31: her daughter | F31: 1771 | G31: 242 | H31: 23 | I31: Book One Part One | J31: Joseph Clark | K31: - | L31: - | M31: Betsey | N31: his wife | O31: Child Female | P31: Mulatto | Q31: Mixed Race | R31: New York | S31: Georgia | T31: New York | U31: Fall 1783 | V31: Port Roseway | W31: Book of Negroes, British Headquarters Papers PRO 30/55/100; Loyalist evacuation shipping lists (1782–1784) | X31: Loyalist evacuation lists | Y31: Robert Turnbull | Z31: Mulatto | AA31: Savannah | AB31: - | AC31: Georgia | AD31: United States | AG31: =IF(AD31="United States", IFERROR(INDEX(Sheet2!$C:$C, MATCH(AE31&AF31, Sheet2!$E:$E, 0)) & ", " & INDEX(Sheet2!$D:$D, MATCH(AE31&AF31, Sheet2!$E:$E, 0)), ""), "-")
A32: Ann | B32: James Jackson 50, thin, goes as pilot (Capt. Mowat). Formerly slave to late Robert Tucker, Norfolk, Virginia; left him with Lord Dunmore when he left that country & was employed as a pilot. | C32: Ship Ann bound for Port Roseway Joseph Clark, Master | D32: James | E32: Jackson 50 | F32: 1733 | G32: 210 | H32: 22 | I32: Book One Part One | J32: Joseph Clark | K32: - | L32: - | M32: - | N32: - | O32: Male | P32: Black | Q32: African American | R32: New York | S32: Virginia | T32: New York | U32: 8 Jul 1783 | V32: Port Roseway | W32: Book of Negroes, British Headquarters Papers PRO 30/55/100; Loyalist evacuation shipping lists (1782–1784) | X32: Loyalist evacuation lists | Y32: Capt. Mowat | Z32: Black | AA32: Norfolk | AB32: - | AC32: Virginia | AD32: United States | AG32: =IF(AD32="United States", IFERROR(INDEX(Sheet2!$C:$C, MATCH(AE32&AF32, Sheet2!$E:$E, 0)) & ", " & INDEX(Sheet2!$D:$D, MATCH(AE32&AF32, Sheet2!$E:$E, 0)), ""), "-")
A33: Ann | B33: Elizabeth Mitchell, 13, stout girl, (Lt. Clows, Guides & Pioneers). Says she was born free near Charlestown, South Carolina; joined the Army in 1780. | C33: Ann bound for St. John's Clark | D33: Elizabeth | E33: Mitchell | F33: 1770 | G33: 1946 | H33: 61 | I33: Book One Part Two | J33: Clark | K33: - | L33: - | M33: - | N33: - | O33: Child Female | P33: Black | Q33: African American | R33: New York | S33: South Carolina | T33: New York | U33: Fall 1783 | V33: St. John's | W33: Book of Negroes, British Headquarters Papers PRO 30/55/100; Loyalist evacuation shipping lists (1782–1784) | X33: Loyalist evacuation lists | Y33: Lt. Clows, Guides & Pioneers | Z33: Black | AA33: Charlestown | AB33: - | AC33: South Carolina | AD33: United States | AG33: =IF(AD33="United States", IFERROR(INDEX(Sheet2!$C:$C, MATCH(AE33&AF33, Sheet2!$E:$E, 0)) & ", " & INDEX(Sheet2!$D:$D, MATCH(AE33&AF33, Sheet2!$E:$E, 0)), ""), "-")
A34: Ann | B34: Dick Vincent, 10, stout boy, (Ens. Vincent). Formerly slave to Charles Vincent, East Chester, grandfather to the Ensign who has delivered the boy to the said Ensign. | C34: Ann bound for St. John's Clark | D34: Dick | E34: Vincent | F34: 1773 | G34: 1947 | H34: 22 | I34: Book One Part Two | J34: Clark | K34: - | L34: - | M34: - | N34: - | O34: Child Male | P34: Black | Q34: African American | R34: New York | S34: - | T34: New York | U34: Fall 1783 | V34: St. John's | W34: Book of Negroes, British Headquarters Papers PRO 30/55/100; Loyalist evacuation shipping lists (1782–1784) | X34: Loyalist evacuation lists | Y34: Ens. Vincent | Z34: Black | AA34: - | AB34: - | AC34: East Chester | AD34: United States | AG34: =IF(AD34="United States", IFERROR(INDEX(Sheet2!$C:$C, MATCH(AE34&AF34, Sheet2!$E:$E, 0)) & ", " & INDEX(Sheet2!$D:$D, MATCH(AE34&AF34, Sheet2!$E:$E, 0)), ""), "-")
A35: Ann | D35: child of | E35: Abigail | F35: - | G35: 250 | H35: 22 | J35: Joseph Clark | O35: c | R35: New York | T35: New York | U35: Fall 1783 | V35: Port Roseway | W35: Book of Negroes, British Headquarters Papers PRO 30/55/100; Loyalist evacuation shipping lists (1782–1784) | X35: Loyalist evacuation lists | Y35: - | AA35: - | AB35: - | AC35: - | AD35: United States | AG35: =IF(AD35="United States", IFERROR(INDEX(Sheet2!$C:$C, MATCH(AE35&AF35, Sheet2!$E:$E, 0)) & ", " & INDEX(Sheet2!$D:$D, MATCH(AE35&AF35, Sheet2!$E:$E, 0)), ""), "-")
A36: Ann | D36: Betsey his | E36: wife | F36: 1750 | G36: 263 | H36: 23 | J36: Joseph Clark | O36: Female | R36: New York | T36: New York | U36: Fall 1783 | V36: Port Roseway | W36: Book of Negroes, British Headquarters Papers PRO 30/55/100; Loyalist evacuation shipping lists (1782–1784) | X36: Loyalist evacuation lists | Y36: - | AA36: - | AB36: - | AC36: - | AD36: United States | AG36: =IF(AD36="United States", IFERROR(INDEX(Sheet2!$C:$C, MATCH(AE36&AF36, Sheet2!$E:$E, 0)) & ", " & INDEX(Sheet2!$D:$D, MATCH(AE36&AF36, Sheet2!$E:$E, 0)), ""), "-")
A37: Ann | D37: Sukey her | E37: daughter | F37: 1771 | G37: 264 | H37: 23 | J37: Joseph Clark | O37: Child Female | R37: New York | T37: New York | U37: Fall 1783 | V37: Port Roseway | W37: Book of Negroes, British Headquarters Papers PRO 30/55/100; Loyalist evacuation shipping lists (1782–1784) | X37: Loyalist evacuation lists | Y37: - | AA37: - | AB37: - | AC37: - | AD37: United States | AG37: =IF(AD37="United States", IFERROR(INDEX(Sheet2!$C:$C, MATCH(AE37&AF37, Sheet2!$E:$E, 0)) & ", " & INDEX(Sheet2!$D:$D, MATCH(AE37&AF37, Sheet2!$E:$E, 0)), ""), "-")
A38: Ann | B38: Betsey his wife, 33, stout mulatto wench, (Robert Turnbull). Formerly slave to Mrs. Harriet Crook, Savannah, Georgia; left that place 5 years ago. | C38: Ship Ann bound for Port Roseway Joseph Clark, Master | D38: Betsey | E38: his wife | F38: 1750 | G38: 241 | H38: 22 | I38: Book One Part One | J38: Joseph Clark | K38: - | L38: - | M38: - | N38: - | O38: Female | P38: Mulatto | Q38: Mixed Race | R38: New York | S38: Georgia | T38: New York | U38: Fall 1783 | V38: Port Roseway | W38: Book of Negroes, British Headquarters Papers PRO 30/55/100; Loyalist evacuation shipping lists (1782–1784) | X38: Loyalist evacuation lists | Y38: Robert Turnbull | Z38: Mulatto | AA38: Savannah | AB38: - | AC38: Georgia | AD38: United States | AG38: =IF(AD38="United States", IFERROR(INDEX(Sheet2!$C:$C, MATCH(AE38&AF38, Sheet2!$E:$E, 0)) & ", " & INDEX(Sheet2!$D:$D, MATCH(AE38&AF38, Sheet2!$E:$E, 0)), ""), "-")
A39: Ann | B39: Judith Jackson, 24, thin wench, mulatto, (Capt. Mowat). Says she served her time to John Bell at Cape Fear and left that with the army of Sir H. Clinton in 1776. | C39: Ship Ann bound for Port Roseway Joseph Clark, Master | D39: Judith | E39: Jackson | F39: 1759 | G39: 211 | H39: 22 | I39: Book One Part One | J39: Joseph Clark | K39: - | L39: - | M39: Betsey | N39: Robertson | O39: Female | P39: Mulatto | Q39: Mixed Race | R39: New York | S39: - | T39: New York | U39: Fall 1783 | V39: Port Roseway | W39: Book of Negroes, British Headquarters Papers PRO 30/55/100; Loyalist evacuation shipping lists (1782–1784) | X39: Loyalist evacuation lists | Y39: Capt. Mowat | Z39: Mulatto | AA39: - | AB39: - | AC39: - | AD39: United States | AG39: =IF(AD39="United States", IFERROR(INDEX(Sheet2!$C:$C, MATCH(AE39&AF39, Sheet2!$E:$E, 0)) & ", " & INDEX(Sheet2!$D:$D, MATCH(AE39&AF39, Sheet2!$E:$E, 0)), ""), "-")
A40: Ann | B40: Harry Jackson, 8, good L boy, (Capt. Mowat). | C40: Ship Ann bound for Port Roseway Joseph Clark, Master | D40: Harry | E40: Jackson | F40: 1775 | G40: 212 | H40: 22 | I40: Book One Part One | J40: Joseph Clark | K40: - | L40: - | M40: - | N40: - | O40: Child Male | P40: Black | Q40: African American | R40: New York | S40: - | T40: New York | U40: Fall 1783 | V40: Port Roseway | W40: Book of Negroes, British Headquarters Papers PRO 30/55/100; Loyalist evacuation shipping lists (1782–1784) | X40: Loyalist evacuation lists | Y40: Capt. Mowat | Z40: Black | AA40: - | AB40: - | AC40: - | AD40: United States | AG40: =IF(AD40="United States", IFERROR(INDEX(Sheet2!$C:$C, MATCH(AE40&AF40, Sheet2!$E:$E, 0)) & ", " & INDEX(Sheet2!$D:$D, MATCH(AE40&AF40, Sheet2!$E:$E, 0)), ""), "-")
A41: Ann | B41: Charles Fox, 33, stout fellow, (John Anderson). Formerly slave to John Fox, Gloster, Virginia; left him about five years ago by proclamation. GBC. | C41: Ship Ann bound for Port Roseway Joseph Clark, Master | D41: Charles | E41: Fox | F41: 1750 | G41: 213 | H41: 22 | I41: Book One Part One | J41: Joseph Clark | K41: - | L41: - | M41: - | N41: - | O41: Male | P41: Black | Q41: African American | R41: New York | S41: Virginia | T41: New York | U41: Fall 1783 | V41: Port Roseway | W41: Book of Negroes, British Headquarters Papers PRO 30/55/100; Loyalist evacuation shipping lists (1782–1784) | X41: Loyalist evacuation lists | Y41: John Anderson | Z41: Black | AA41: Gloster | AB41: - | AC41: Virginia | AD41: United States | AG41: =IF(AD41="United States", IFERROR(INDEX(Sheet2!$C:$C, MATCH(AE41&AF41, Sheet2!$E:$E, 0)) & ", " & INDEX(Sheet2!$D:$D, MATCH(AE41&AF41, Sheet2!$E:$E, 0)), ""), "-")
A42: Ann | B42: Peter Warner, 30, stout, cut above his left eye, (William Hill). Formerly slave to Michael Mount, Monmouth, New Jersey; left him 5 years ago. GBC. | C42: Ship Ann bound for Port Roseway Joseph Clark, Master | D42: Peter | E42: Warner | F42: 1753 | G42: 235 | H42: 22 | I42: Book One Part One | J42: Joseph Clark | K42: - | L42: - | M42: - | N42: - | O42: Male | P42: Black | Q42: African American | R42: New York | S42: New Jersey | T42: New York | U42: Fall 1783 | V42: Port Roseway | W42: Book of Negroes, British Headquarters Papers PRO 30/55/100; Loyalist evacuation shipping lists (1782–1784) | X42: Loyalist evacuation lists | Y42: William Hill | Z42: Black | AA42: Monmouth | AB42: - | AC42: New Jersey | AD42: United States | AG42: =IF(AD42="United States", IFERROR(INDEX(Sheet2!$C:$C, MATCH(AE42&AF42, Sheet2!$E:$E, 0)) & ", " & INDEX(Sheet2!$D:$D, MATCH(AE42&AF42, Sheet2!$E:$E, 0)), ""), "-")
A43: Ann | B43: Casar Nicholls, 22, stout black man, (William Hill). Formerly slave to Dr. Van Wyck at Fishkills; left him 3½ years ago. | C43: Ship Ann bound for Port Roseway Joseph Clark, Master | D43: Casar | E43: Nicholls | F43: 1761 | G43: 234 | H43: - | I43: Book One Part One | J43: Joseph Clark | K43: - | L43: - | M43: - | N43: - | O43: Male | P43: Black | Q43: African American | R43: - | S43: - | T43: - | U43: - | V43: Port Roseway | W43: - | X43: - | Y43: William Hill | Z43: Black | AA43: - | AB43: - | AC43: - | AD43: United States | AG43: =IF(AD43="United States", IFERROR(INDEX(Sheet2!$C:$C, MATCH(AE43&AF43, Sheet2!$E:$E, 0)) & ", " & INDEX(Sheet2!$D:$D, MATCH(AE43&AF43, Sheet2!$E:$E, 0)), ""), "-")
A44: Ann | B44: Judah Pell, 25, S.B. Wench, child 5 yrs, old, (William Hill). Formerly slave to Dr. Ramsey, Norfolk, Virginia; left him about five years ago. | C44: Ship Ann bound for Port Roseway Joseph Clark, Master | D44: Judah | E44: Pell | F44: 1758 | G44: 233 | H44: 22 | I44: Book One Part One | J44: Joseph Clark | K44: - | L44: - | M44: - | N44: - | O44: Child Female | P44: Black | Q44: African American | R44: New York | S44: Virginia | T44: New York | U44: Fall 1783 | V44: Port Roseway | W44: Book of Negroes, British Headquarters Papers PRO 30/55/100; Loyalist evacuation shipping lists (1782–1784) | X44: Loyalist evacuation lists | Y44: William Hill | Z44: Black | AA44: Norfolk | AB44: - | AC44: Virginia | AD44: United States | AG44: =IF(AD44="United States", IFERROR(INDEX(Sheet2!$C:$C, MATCH(AE44&AF44, Sheet2!$E:$E, 0)) & ", " & INDEX(Sheet2!$D:$D, MATCH(AE44&AF44, Sheet2!$E:$E, 0)), ""), "-")
A45: Ann | B45: John Pell, 14, stout mulatto boy, (William Hill). Son to the above mentioned person. | C45: Ship Ann bound for Port Roseway Joseph Clark, Master | D45: John | E45: Pell | F45: 1769 | G45: 232 | H45: 22 | I45: Book One Part One | J45: Joseph Clark | K45: - | L45: - | M45: - | N45: - | O45: Child Male | P45: Mulatto | Q45: Mixed Race | R45: New York | S45: - | T45: New York | U45: Fall 1783 | V45: Port Roseway | W45: Book of Negroes, British Headquarters Papers PRO 30/55/100; Loyalist evacuation shipping lists (1782–1784) | X45: Loyalist evacuation lists | Y45: William Hill | Z45: Mulatto | AA45: - | AB45: - | AC45: - | AD45: United States | AG45: =IF(AD45="United States", IFERROR(INDEX(Sheet2!$C:$C, MATCH(AE45&AF45, Sheet2!$E:$E, 0)) & ", " & INDEX(Sheet2!$D:$D, MATCH(AE45&AF45, Sheet2!$E:$E, 0)), ""), "-")
A46: Ann | B46: John Pell, 28, stout man, pock marked, (William Hill). Free as appears by a Certificate of General Birch to whom he was given by Sir Henry Clinton; says he left Charlestown about 5 years ago. | C46: Ship Ann bound for Port Roseway Joseph Clark, Master | D46: John | E46: Pell | F46: 1755 | G46: 231 | H46: 22 | I46: Book One Part One | J46: Joseph Clark | K46: - | L46: - | M46: - | N46: - | O46: Male | P46: Black | Q46: African American | R46: New York | S46: - | T46: New York | U46: Fall 1783 | V46: Port Roseway | W46: Book of Negroes, British Headquarters Papers PRO 30/55/100; Loyalist evacuation shipping lists (1782–1784) | X46: Loyalist evacuation lists | Y46: William Hill | Z46: Black | AA46: - | AB46: - | AC46: Charlestown | AD46: United States | AG46: =IF(AD46="United States", IFERROR(INDEX(Sheet2!$C:$C, MATCH(AE46&AF46, Sheet2!$E:$E, 0)) & ", " & INDEX(Sheet2!$D:$D, MATCH(AE46&AF46, Sheet2!$E:$E, 0)), ""), "-")
A47: Ann | B47: Abigail, 35, stout child 4 mo. (Thomas Statia). Formerly slave to White at Brunswick, New Jersey; left him five years ago. | C47: Ship Ann bound for Port Roseway Joseph Clark, Master | D47: Abigail | E47: - | F47: 1748 | G47: 230 | H47: 22 | I47: Book One Part One | J47: Joseph Clark | K47: - | L47: - | M47: - | N47: - | O47: Child Male | P47: Black | Q47: African American | R47: New York | S47: New Jersey | T47: New York | U47: Fall 1783 | V47: Port Roseway | W47: Book of Negroes, British Headquarters Papers PRO 30/55/100; Loyalist evacuation shipping lists (1782–1784) | X47: Loyalist evacuation lists | Y47: Thomas Statia | Z47: Black | AA47: mo | AB47: Brunswick | AC47: New Jersey | AD47: United States | AG47: =IF(AD47="United States", IFERROR(INDEX(Sheet2!$C:$C, MATCH(AE47&AF47, Sheet2!$E:$E, 0)) & ", " & INDEX(Sheet2!$D:$D, MATCH(AE47&AF47, Sheet2!$E:$E, 0)), ""), "-")
A48: Ann | B48: Judah Few, 35, stout M wench, child 5 years old. (Robert McCulloch). Free born, James Way's, English Kills, Newtown, Long Island. | C48: Ship Ann bound for Port Roseway Joseph Clark, Master | D48: Judah | E48: Few | F48: 1748 | G48: 229 | H48: 22 | I48: Book One Part One | J48: Joseph Clark | K48: - | L48: - | M48: - | N48: - | O48: Child Female | P48: Black | Q48: African American | R48: New York | S48: - | T48: New York | U48: Fall 1783 | V48: Port Roseway | W48: Book of Negroes, British Headquarters Papers PRO 30/55/100; Loyalist evacuation shipping lists (1782–1784) | X48: Loyalist evacuation lists | Y48: Robert McCulloch | Z48: Black | AA48: English Kills | AB48: Newtown | AC48: Long Island | AD48: United States | AG48: =IF(AD48="United States", IFERROR(INDEX(Sheet2!$C:$C, MATCH(AE48&AF48, Sheet2!$E:$E, 0)) & ", " & INDEX(Sheet2!$D:$D, MATCH(AE48&AF48, Sheet2!$E:$E, 0)), ""), "-")
A49: Ann | B49: Prince Few, 26, thin mulatto, (Robert McCulloch). Free born, Pearson town, Connecticut. | C49: Ship Ann bound for Port Roseway Joseph Clark, Master | D49: Prince | E49: Few | F49: 1757 | G49: 228 | H49: 22 | I49: Book One Part One | J49: Joseph Clark | K49: - | L49: - | M49: - | N49: - | O49: Male | P49: Mulatto | Q49: Mixed Race | R49: New York | S49: - | T49: New York | U49: Fall 1783 | V49: Port Roseway | W49: Book of Negroes, British Headquarters Papers PRO 30/55/100; Loyalist evacuation shipping lists (1782–1784) | X49: Loyalist evacuation lists | Y49: Robert McCulloch | Z49: Mulatto | AA49: - | AB49: - | AC49: Connecticut | AD49: United States | AG49: =IF(AD49="United States", IFERROR(INDEX(Sheet2!$C:$C, MATCH(AE49&AF49, Sheet2!$E:$E, 0)) & ", " & INDEX(Sheet2!$D:$D, MATCH(AE49&AF49, Sheet2!$E:$E, 0)), ""), "-")
... A74: Ann & Elizabeth | B74: Dinah his wife, 23, lusty, squat wench, B, small child (Nicholas Browne). Born free, her mother an Indian; served her time with Edmund Palmer who lived & was hanged at Fishkill for being Tory. | C74: Ship Ann & Elizabeth bound for Port Roseway Ben Fowler, Master | D74: Dinah | E74: his wife | F74: 1760 | G74: 432 | H74: 27 | I74: Book One Part One | J74: Ben Fowler | K74: - | L74: - | M74: Dinah | N74: Edmonds | O74: Child Female | P74: Black | Q74: Mixed Race | R74: New York | S74: - | T74: New York | U74: 1783 | V74: Port Roseway | W74: Book of Negroes, British Headquarters Papers PRO 30/55/100; Loyalist evacuation shipping lists (1782–1784) | X74: Book of Negroes | Y74: Nicholas Browne | Z74: Black | AA74: - | AB74: - | AC74: Fishkill | AD74: United States | AG74: =IF(AD74="United States", IFERROR(INDEX(Sheet2!$C:$C, MATCH(AE74&AF74, Sheet2!$E:$E, 0)) & ", " & INDEX(Sheet2!$D:$D, MATCH(AE74&AF74, Sheet2!$E:$E, 0)), ""), "-")
A75: Ann & Elizabeth | D75: Nancy his | E75: wife | F75: 1743 | G75: 478 | H75: 27 | J75: Ben Fowler | O75: Female | R75: New York | T75: New York | U75: 1783 | V75: Port Roseway | W75: Book of Negroes, British Headquarters Papers PRO 30/55/100; Loyalist evacuation shipping lists (1782–1784) | X75: Book of Negroes | Y75: - | AA75: - | AB75: - | AC75: - | AD75: United States | AG75: =IF(AD75="United States", IFERROR(INDEX(Sheet2!$C:$C, MATCH(AE75&AF75, Sheet2!$E:$E, 0)) & ", " & INDEX(Sheet2!$D:$D, MATCH(AE75&AF75, Sheet2!$E:$E, 0)), ""), "-")
A76: Ann & Elizabeth | D76: Dinah Browne his | E76: wife | F76: 1760 | G76: 475 | H76: 27 | J76: Ben Fowler | O76: Female | R76: New York | T76: New York | U76: 1783 | V76: Port Roseway | W76: Book of Negroes, British Headquarters Papers PRO 30/55/100; Loyalist evacuation shipping lists (1782–1784) | X76: Book of Negroes | Y76: - | AA76: - | AB76: - | AC76: - | AD76: United States | AG76: =IF(AD76="United States", IFERROR(INDEX(Sheet2!$C:$C, MATCH(AE76&AF76, Sheet2!$E:$E, 0)) & ", " & INDEX(Sheet2!$D:$D, MATCH(AE76&AF76, Sheet2!$E:$E, 0)), ""), "-")
A77: Ann & Elizabeth | D77: child of | E77: Hannah | F77: - | G77: 473 | H77: 27 | J77: Ben Fowler | O77: c | R77: New York | T77: New York | U77: 1783 | V77: Port Roseway | W77: Book of Negroes, British Headquarters Papers PRO 30/55/100; Loyalist evacuation shipping lists (1782–1784) | X77: Book of Negroes | Y77: - | AA77: - | AB77: - | AC77: - | AD77: United States | AG77: =IF(AD77="United States", IFERROR(INDEX(Sheet2!$C:$C, MATCH(AE77&AF77, Sheet2!$E:$E, 0)) & ", " & INDEX(Sheet2!$D:$D, MATCH(AE77&AF77, Sheet2!$E:$E, 0)), ""), "-")
A78: Ann & Elizabeth | D78: child of | E78: Hannah | F78: - | G78: 472 | H78: 27 | J78: Ben Fowler | O78: c | R78: New York | T78: New York | U78: 1783 | V78: Port Roseway | W78: Book of Negroes, British Headquarters Papers PRO 30/55/100; Loyalist evacuation shipping lists (1782–1784) | X78: Book of Negroes | Y78: - | AA78: - | AB78: - | AC78: - | AD78: United States | AG78: =IF(AD78="United States", IFERROR(INDEX(Sheet2!$C:$C, MATCH(AE78&AF78, Sheet2!$E:$E, 0)) & ", " & INDEX(Sheet2!$D:$D, MATCH(AE78&AF78, Sheet2!$E:$E, 0)), ""), "-")
A79: Ann & Elizabeth | D79: Hannah his | E79: wife | F79: 1760 | G79: 471 | H79: 27 | J79: Ben Fowler | O79: Female | R79: New York | T79: New York | U79: 1783 | V79: Port Roseway | W79: Book of Negroes, British Headquarters Papers PRO 30/55/100; Loyalist evacuation shipping lists (1782–1784) | X79: Book of Negroes | Y79: - | AA79: - | AB79: - | AC79: - | AD79: United States | AG79: =IF(AD79="United States", IFERROR(INDEX(Sheet2!$C:$C, MATCH(AE79&AF79, Sheet2!$E:$E, 0)) & ", " & INDEX(Sheet2!$D:$D, MATCH(AE79&AF79, Sheet2!$E:$E, 0)), ""), "-")
A80: Ann & Elizabeth | B80: Tom, 40, sickly man, (Thomas Hartley). Formerly slave to Henry Smith, Charlestown, South Carolina, who died soon after it was taken by the British; left no heirs. | C80: Ship Ann & Elizabeth bound for Port Roseway Ben Fowler, Master | D80: Tom | E80: - | F80: 1743 | G80: 433 | H80: 27 | I80: Book One Part One | J80: Ben Fowler | K80: - | L80: - | M80: - | N80: - | O80: Male | P80: Black | Q80: African American | R80: New York | S80: South Carolina | T80: New York | U80: 1783 | V80: Port Roseway | W80: Book of Negroes, British Headquarters Papers PRO 30/55/100; Loyalist evacuation shipping lists (1782–1784) | X80: Book of Negroes | Y80: Thomas Hartley | Z80: Black | AA80: Charlestown | AB80: - | AC80: South Carolina | AD80: United States | AG80: =IF(AD80="United States", IFERROR(INDEX(Sheet2!$C:$C, MATCH(AE80&AF80, Sheet2!$E:$E, 0)) & ", " & INDEX(Sheet2!$D:$D, MATCH(AE80&AF80, Sheet2!$E:$E, 0)), ""), "-")
A81: Ann & Elizabeth | B81: George Barnes, 47, feeble fellow, goes as Cook to the Ship. Says he is a free man; produces a Certificate dated 1770 from John Davis of Newport, Rhode Island, Justice of the Peace. | C81: Ann & Elizabeth bound for Spithead & Germany Ben Fowler | D81: George | E81: Barnes | F81: 1736 | G81: 1798 | H81: 58 | I81: Book One Part Two | J81: - | K81: - | L81: - | M81: - | N81: - | O81: Male | P81: Black | Q81: African American | R81: New York | S81: - | T81: New York | U81: 1783 | V81: - | W81: Book of Negroes, British Headquarters Papers PRO 30/55/100; Loyalist evacuation shipping lists (1782–1784) | X81: Book of Negroes | Y81: - | Z81: Black | AA81: Newport | AB81: Rhode Island | AC81: Peace | AD81: United States | AG81: =IF(AD81="United States", IFERROR(INDEX(Sheet2!$C:$C, MATCH(AE81&AF81, Sheet2!$E:$E, 0)) & ", " & INDEX(Sheet2!$D:$D, MATCH(AE81&AF81, Sheet2!$E:$E, 0)), ""), "-")
A82: Ann & Elizabeth | B82: Prince Fraction, 25, stout blind left eye, Edward Trigler of Port Roseway, claimant (Edward Trigler). Property of Edward Trigler, purchased from James Stokes of New York. | C82: Ship Ann & Elizabeth bound for Port Roseway Ben Fowler, Master | D82: Prince | E82: Fraction | F82: 1758 | G82: 435 | H82: 27 | I82: Book One Part One | J82: Ben Fowler | K82: - | L82: - | M82: - | N82: - | O82: Male | P82: Black | Q82: African American | R82: New York | S82: New York | T82: New York | U82: 1783 | V82: Port Roseway | W82: Book of Negroes, British Headquarters Papers PRO 30/55/100; Loyalist evacuation shipping lists (1782–1784) | X82: Book of Negroes | Y82: Edward Trigler | Z82: Black | AA82: - | AB82: - | AC82: New York | AD82: United States | AG82: =IF(AD82="United States", IFERROR(INDEX(Sheet2!$C:$C, MATCH(AE82&AF82, Sheet2!$E:$E, 0)) & ", " & INDEX(Sheet2!$D:$D, MATCH(AE82&AF82, Sheet2!$E:$E, 0)), ""), "-")
A83: Ann & Elizabeth | B83: Nancy his wife, 40, thin wench, (Thomas Hartley). Formerly slave to Widow Lott of Charlestown Elliot of Charlestown who she says gave her free before she died 11 years ago. | C83: Ship Ann & Elizabeth bound for Port Roseway Ben Fowler, Master | D83: Nancy | E83: his wife | F83: 1743 | G83: 434 | H83: 27 | I83: Book One Part One | J83: Ben Fowler | K83: - | L83: - | M83: - | N83: - | O83: Female | P83: Black | Q83: African American | R83: New York | S83: - | T83: New York | U83: 1783 | V83: Port Roseway | W83: Book of Negroes, British Headquarters Papers PRO 30/55/100; Loyalist evacuation shipping lists (1782–1784) | X83: Book of Negroes | Y83: Thomas Hartley | Z83: Black | AA83: - | AB83: - | AC83: Charlestown | AD83: United States | AG83: =IF(AD83="United States", IFERROR(INDEX(Sheet2!$C:$C, MATCH(AE83&AF83, Sheet2!$E:$E, 0)) & ", " & INDEX(Sheet2!$D:$D, MATCH(AE83&AF83, Sheet2!$E:$E, 0)), ""), "-")
A84: Ann & Elizabeth | B84: Peter Johnson, 35, stout fellow, (Stephen Shakespeare). Says he got his freedom from Silvester Brinoly, Quaker, New Jersey; that he has lived in New York these 6 years past. GBC. | C84: Ship Ann & Elizabeth bound for Port Roseway Ben Fowler, Master | D84: Peter | E84: Johnson | F84: 1748 | G84: 416 | H84: 27 | I84: Book One Part One | J84: Ben Fowler | K84: John | L84: Voice | M84: - | N84: - | O84: Male | P84: Black | Q84: African American | R84: New York | S84: New Jersey | T84: New York | U84: 1783 | V84: Port Roseway | W84: Book of Negroes, British Headquarters Papers PRO 30/55/100; Loyalist evacuation shipping lists (1782–1784) | X84: Book of Negroes | Y84: Stephen Shakespeare | Z84: Black | AA84: New Jersey | AB84: - | AC84: New York | AD84: United States | AG84: =IF(AD84="United States", IFERROR(INDEX(Sheet2!$C:$C, MATCH(AE84&AF84, Sheet2!$E:$E, 0)) & ", " & INDEX(Sheet2!$D:$D, MATCH(AE84&AF84, Sheet2!$E:$E, 0)), ""), "-")
A85: Ann & Elizabeth | B85: Judith Johnson, 27, ordinary wench, (Stephen Shakespeare). Formerly slave to Gerrit Langston, Shrewsbury; left him 3 years past. GBC. | C85: Ship Ann & Elizabeth bound for Port Roseway Ben Fowler, Master | D85: Judith | E85: Johnson | F85: 1756 | G85: 417 | H85: 27 | I85: Book One Part One | J85: Ben Fowler | K85: - | L85: - | M85: - | N85: - | O85: Female | P85: Black | Q85: African American | R85: New York | S85: - | T85: New York | U85: 1783 | V85: Port Roseway | W85: Book of Negroes, British Headquarters Papers PRO 30/55/100; Loyalist evacuation shipping lists (1782–1784) | X85: Book of Negroes | Y85: Stephen Shakespeare | Z85: Black | AA85: - | AB85: - | AC85: Shrewsbury | AD85: United States | AG85: =IF(AD85="United States", IFERROR(INDEX(Sheet2!$C:$C, MATCH(AE85&AF85, Sheet2!$E:$E, 0)) & ", " & INDEX(Sheet2!$D:$D, MATCH(AE85&AF85, Sheet2!$E:$E, 0)), ""), "-")
A86: Ann & Elizabeth | B86: Thomas Danvers, 45, ordinary fellow, (Archibald Clarke). Formerly slave to Thomas Brown, Savannah; left him 5 years past. | C86: Ship Ann & Elizabeth bound for Port Roseway Ben Fowler, Master | D86: Thomas | E86: Danvers | F86: 1738 | G86: 418 | H86: 27 | I86: Book One Part One | J86: Ben Fowler | K86: - | L86: - | M86: - | N86: - | O86: Male | P86: Black | Q86: African American | R86: New York | S86: - | T86: New York | U86: 1783 | V86: Port Roseway | W86: Book of Negroes, British Headquarters Papers PRO 30/55/100; Loyalist evacuation shipping lists (1782–1784) | X86: Book of Negroes | Y86: Archibald Clarke | Z86: Black | AA86: - | AB86: - | AC86: Savannah | AD86: United States | AG86: =IF(AD86="United States", IFERROR(INDEX(Sheet2!$C:$C, MATCH(AE86&AF86, Sheet2!$E:$E, 0)) & ", " & INDEX(Sheet2!$D:$D, MATCH(AE86&AF86, Sheet2!$E:$E, 0)), ""), "-")
A87: Ann & Elizabeth | B87: Rachel, 7, fine child. Daughter to George Barnes. | C87: Ann & Elizabeth bound for Spithead & Germany Ben Fowler | D87: Rachel | E87: - | F87: 1776 | G87: 1799 | H87: 58 | I87: Book One Part Two | J87: - | K87: - | L87: - | M87: - | N87: - | O87: Child Male | P87: Black | Q87: African American | R87: New York | S87: - | T87: New York | U87: 1783 | V87: - | W87: Book of Negroes, British Headquarters Papers PRO 30/55/100; Loyalist evacuation shipping lists (1782–1784) | X87: Book of Negroes | Y87: - | Z87: Black | AA87: - | AB87: - | AC87: - | AD87: United States | AG87: =IF(AD87="United States", IFERROR(INDEX(Sheet2!$C:$C, MATCH(AE87&AF87, Sheet2!$E:$E, 0)) & ", " & INDEX(Sheet2!$D:$D, MATCH(AE87&AF87, Sheet2!$E:$E, 0)), ""), "-")
A88: Ann & Elizabeth | B88: Harry Spencell, 38, slender fellow, (Stephen Hairran). Formerly slave to B. Benson left him on the Landing of the British troops on New York Island. | C88: Ship Ann & Elizabeth bound for Port Roseway Ben Fowler, Master | D88: Harry | E88: Spencell | F88: 1745 | G88: 420 | H88: 27 | I88: Book One Part One | J88: Ben Fowler | K88: - | L88: - | M88: - | N88: - | O88: Male | P88: Black | Q88: African American | R88: New York | S88: New York | T88: New York | U88: 1783 | V88: Port Roseway | W88: Book of Negroes, British Headquarters Papers PRO 30/55/100; Loyalist evacuation shipping lists (1782–1784) | X88: Book of Negroes | Y88: Stephen Hairran | Z88: Black | AA88: - | AB88: - | AC88: New York Island | AD88: United States | AG88: =IF(AD88="United States", IFERROR(INDEX(Sheet2!$C:$C, MATCH(AE88&AF88, Sheet2!$E:$E, 0)) & ", " & INDEX(Sheet2!$D:$D, MATCH(AE88&AF88, Sheet2!$E:$E, 0)), ""), "-")
A89: Ann & Elizabeth | B89: Henry Maxfield, 33, stout fellow, (Alexander Watson). Free born in Mr. Philips's house of Philips's Manor. GBC. | C89: Ship Ann & Elizabeth bound for Port Roseway Ben Fowler, Master | D89: Henry | E89: Maxfield | F89: 1750 | G89: 429 | H89: 27 | I89: Book One Part One | J89: Ben Fowler | K89: - | L89: - | M89: - | N89: - | O89: Male | P89: Black | Q89: African American | R89: New York | S89: - | T89: New York | U89: 1783 | V89: Port Roseway | W89: Book of Negroes, British Headquarters Papers PRO 30/55/100; Loyalist evacuation shipping lists (1782–1784) | X89: Book of Negroes | Y89: Alexander Watson | Z89: Black | AA89: - | AB89: - | AC89: - | AD89: United States | AG89: =IF(AD89="United States", IFERROR(INDEX(Sheet2!$C:$C, MATCH(AE89&AF89, Sheet2!$E:$E, 0)) & ", " & INDEX(Sheet2!$D:$D, MATCH(AE89&AF89, Sheet2!$E:$E, 0)), ""), "-")
A90: Ann & Elizabeth | B90: John Rogers, 29, stout fellow, (Andrew Gibson). Formerly slave to Captain Rogers, Brig Dispatch, who went to England and left him free. | C90: Ship Ann & Elizabeth bound for Port Roseway Ben Fowler, Master | D90: John | E90: Rogers | F90: 1754 | G90: 428 | H90: 27 | I90: Book One Part One | J90: Ben Fowler | K90: - | L90: - | M90: - | N90: - | O90: Male | P90: Black | Q90: African American | R90: New York | S90: - | T90: New York | U90: 1783 | V90: Port Roseway | W90: Book of Negroes, British Headquarters Papers PRO 30/55/100; Loyalist evacuation shipping lists (1782–1784) | X90: Book of Negroes | Y90: Andrew Gibson | Z90: Black | AA90: - | AB90: - | AC90: England | AD90: England | AG90: =IF(AD90="United States", IFERROR(INDEX(Sheet2!$C:$C, MATCH(AE90&AF90, Sheet2!$E:$E, 0)) & ", " & INDEX(Sheet2!$D:$D, MATCH(AE90&AF90, Sheet2!$E:$E, 0)), ""), "52.5310214, -1.2649062") -> 52.5310214, -1.2649062
A91: Ann & Elizabeth | B91: Thomas Edmonds, 5, small boy, (Stephen Shakespeare). Formerly slave to Mr. Edmonds, Charlestown; left him 5 years past. | C91: Ship Ann & Elizabeth bound for Port Roseway Ben Fowler, Master | D91: Thomas | E91: Edmonds | F91: 1778 | G91: 427 | H91: 27 | I91: Book One Part One | J91: Ben Fowler | K91: - | L91: - | M91: - | N91: - | O91: Child Male | P91: Black | Q91: African American | R91: New York | S91: - | T91: New York | U91: 1783 | V91: Port Roseway | W91: Book of Negroes, British Headquarters Papers PRO 30/55/100; Loyalist evacuation shipping lists (1782–1784) | X91: Book of Negroes | Y91: Stephen Shakespeare | Z91: Black | AA91: - | AB91: - | AC91: Charlestown | AD91: United States | AG91: =IF(AD91="United States", IFERROR(INDEX(Sheet2!$C:$C, MATCH(AE91&AF91, Sheet2!$E:$E, 0)) & ", " & INDEX(Sheet2!$D:$D, MATCH(AE91&AF91, Sheet2!$E:$E, 0)), ""), "-")
A92: Ann & Elizabeth | B92: Bill Browne, 24, stout fellow, (Nicholas Browne). Formerly slave to Jacob Arnold, Morristown, New Jersey; left him three years ago. | C92: Ship Ann & Elizabeth bound for Port Roseway Ben Fowler, Master | D92: Bill | E92: Browne | F92: 1759 | G92: 431 | H92: 27 | I92: Book One Part One | J92: Ben Fowler | K92: - | L92: - | M92: - | N92: - | O92: Male | P92: Black | Q92: African American | R92: New York | S92: New Jersey | T92: New York | U92: 1783 | V92: Port Roseway | W92: Book of Negroes, British Headquarters Papers PRO 30/55/100; Loyalist evacuation shipping lists (1782–1784) | X92: Book of Negroes | Y92: Nicholas Browne | Z92: Black | AA92: Morristown | AB92: - | AC92: New Jersey | AD92: United States | AG92: =IF(AD92="United States", IFERROR(INDEX(Sheet2!$C:$C, MATCH(AE92&AF92, Sheet2!$E:$E, 0)) & ", " & INDEX(Sheet2!$D:$D, MATCH(AE92&AF92, Sheet2!$E:$E, 0)), ""), "-")
A93: Ann & Elizabeth | B93: Dinah Edmonds, 34, ordinary wench, (Stephen Shakespeare). Formerly slave to Mr. Edmonds, Charlestown; left him 5 years past. | C93: Ship Ann & Elizabeth bound for Port Roseway Ben Fowler, Master | D93: Dinah | E93: Edmonds | F93: 1749 | G93: 426 | H93: 27 | I93: Book One Part One | J93: Ben Fowler | K93: - | L93: - | M93: - | N93: - | O93: Female | P93: Black | Q93: African American | R93: New York | S93: - | T93: New York | U93: 1783 | V93: Port Roseway | W93: Book of Negroes, British Headquarters Papers PRO 30/55/100; Loyalist evacuation shipping lists (1782–1784) | X93: Book of Negroes | Y93: Stephen Shakespeare | Z93: Black | AA93: - | AB93: - | AC93: Charlestown | AD93: United States | AG93: =IF(AD93="United States", IFERROR(INDEX(Sheet2!$C:$C, MATCH(AE93&AF93, Sheet2!$E:$E, 0)) & ", " & INDEX(Sheet2!$D:$D, MATCH(AE93&AF93, Sheet2!$E:$E, 0)), ""), "-")
A94: Ann & Elizabeth | B94: Cath Drayton, 40, ordinary wench, (Edward Hannah). Formerly slave to Mrs. Drayton near Charlestown; left her before the Siege of Charlestown. | C94: Ship Ann & Elizabeth bound for Port Roseway Ben Fowler, Master | D94: Cath | E94: Drayton | F94: 1743 | G94: 425 | H94: 27 | I94: Book One Part One | J94: Ben Fowler | K94: - | L94: - | M94: - | N94: - | O94: Female | P94: Black | Q94: African American | R94: New York | S94: - | T94: New York | U94: 1783 | V94: Port Roseway | W94: Book of Negroes, British Headquarters Papers PRO 30/55/100; Loyalist evacuation shipping lists (1782–1784) | X94: Book of Negroes | Y94: Edward Hannah | Z94: Black | AA94: - | AB94: - | AC94: Charlestown | AD94: United States | AG94: =IF(AD94="United States", IFERROR(INDEX(Sheet2!$C:$C, MATCH(AE94&AF94, Sheet2!$E:$E, 0)) & ", " & INDEX(Sheet2!$D:$D, MATCH(AE94&AF94, Sheet2!$E:$E, 0)), ""), "-")
A95: Ann & Elizabeth | B95: Sarah Cross, 34, stout squat wench, M, (Archibald Clarke). Says she was born free at Tappan, served her time to James Rickman, New York Island. | C95: Ship Ann & Elizabeth bound for Port Roseway Ben Fowler, Master | D95: Sarah | E95: Cross | F95: 1749 | G95: 419 | H95: 27 | I95: Book One Part One | J95: Ben Fowler | K95: - | L95: - | M95: - | N95: - | O95: Female | P95: Black | Q95: African American | R95: New York | S95: New York | T95: New York | U95: 1783 | V95: Port Roseway | W95: Book of Negroes, British Headquarters Papers PRO 30/55/100; Loyalist evacuation shipping lists (1782–1784) | X95: Book of Negroes | Y95: Archibald Clarke | Z95: Black | AA95: Tappan | AB95: - | AC95: New York Island | AD95: United States | AG95: =IF(AD95="United States", IFERROR(INDEX(Sheet2!$C:$C, MATCH(AE95&AF95, Sheet2!$E:$E, 0)) & ", " & INDEX(Sheet2!$D:$D, MATCH(AE95&AF95, Sheet2!$E:$E, 0)), ""), "-")
A96: Ann & Elizabeth | B96: Hannah his wife, 23, stout wench, 2 small children, (Alexander Watson). Free born in John Predun, Closters, New Jersey. | C96: Ship Ann & Elizabeth bound for Port Roseway Ben Fowler, Master | D96: Hannah | E96: his wife | F96: 1760 | G96: 430 | H96: 27 | I96: Book One Part One | J96: Ben Fowler | K96: Henry | L96: Maxfield | M96: - | N96: - | O96: Child Female | P96: Black | Q96: African American | R96: New York | S96: New Jersey | T96: New York | U96: 1783 | V96: Port Roseway | W96: Book of Negroes, British Headquarters Papers PRO 30/55/100; Loyalist evacuation shipping lists (1782–1784) | X96: Book of Negroes | Y96: Alexander Watson | Z96: Black | AA96: - | AB96: - | AC96: New Jersey | AD96: United States | AG96: =IF(AD96="United States", IFERROR(INDEX(Sheet2!$C:$C, MATCH(AE96&AF96, Sheet2!$E:$E, 0)) & ", " & INDEX(Sheet2!$D:$D, MATCH(AE96&AF96, Sheet2!$E:$E, 0)), ""), "-")
A97: Ann & Elizabeth | B97: Samuel Drayton, 40, stout fellow, (Edward Hannah). Formerly slave to Mrs. Drayton near Charlestown; left her before the Siege of Charlestown. | C97: Ship Ann & Elizabeth bound for Port Roseway Ben Fowler, Master | D97: Samuel | E97: Drayton | F97: 1743 | G97: 424 | H97: 27 | I97: Book One Part One | J97: Ben Fowler | K97: - | L97: - | M97: - | N97: - | O97: Male | P97: Black | Q97: African American | R97: New York | S97: - | T97: New York | U97: 1783 | V97: Port Roseway | W97: Book of Negroes, British Headquarters Papers PRO 30/55/100; Loyalist evacuation shipping lists (1782–1784) | X97: Book of Negroes | Y97: Edward Hannah | Z97: Black | AA97: - | AB97: - | AC97: Charlestown | AD97: United States | AG97: =IF(AD97="United States", IFERROR(INDEX(Sheet2!$C:$C, MATCH(AE97&AF97, Sheet2!$E:$E, 0)) & ", " & INDEX(Sheet2!$D:$D, MATCH(AE97&AF97, Sheet2!$E:$E, 0)), ""), "-")
A98: Ann & Elizabeth | B98: Venus, 28, slender wench, (Edward Hannah). Formerly slave to William Smith, Charlestown; left him about 5 years past. | C98: Ship Ann & Elizabeth bound for Port Roseway Ben Fowler, Master | D98: Venus | E98: - | F98: 1755 | G98: 423 | H98: 27 | I98: Book One Part One | J98: Ben Fowler | K98: - | L98: - | M98: - | N98: - | O98: Female | P98: Black | Q98: African American | R98: New York | S98: - | T98: New York | U98: 1783 | V98: Port Roseway | W98: Book of Negroes, British Headquarters Papers PRO 30/55/100; Loyalist evacuation shipping lists (1782–1784) | X98: Book of Negroes | Y98: Edward Hannah | Z98: Black | AA98: - | AB98: - | AC98: Charlestown | AD98: United States | AG98: =IF(AD98="United States", IFERROR(INDEX(Sheet2!$C:$C, MATCH(AE98&AF98, Sheet2!$E:$E, 0)) & ", " & INDEX(Sheet2!$D:$D, MATCH(AE98&AF98, Sheet2!$E:$E, 0)), ""), "-")
A99: Ann & Elizabeth | B99: Jack Smith, 25, slender fellow, (Edward Hannah). Formerly slave to William Smith, Charlestown; left him about 5 years past. | C99: Ship Ann & Elizabeth bound for Port Roseway Ben Fowler, Master | D99: Jack | E99: Smith | F99: 1758 | G99: 422 | H99: 27 | I99: Book One Part One | J99: Ben Fowler | K99: - | L99: - | M99: - | N99: - | O99: Male | P99: Black | Q99: African American | R99: New York | S99: - | T99: New York | U99: 1783 | V99: Port Roseway | W99: Book of Negroes, British Headquarters Papers PRO 30/55/100; Loyalist evacuation shipping lists (1782–1784) | X99: Book of Negroes | Y99: Edward Hannah | Z99: Black | AA99: - | AB99: - | AC99: Charlestown | AD99: United States | AG99: =IF(AD99="United States", IFERROR(INDEX(Sheet2!$C:$C, MATCH(AE99&AF99, Sheet2!$E:$E, 0)) & ", " & INDEX(Sheet2!$D:$D, MATCH(AE99&AF99, Sheet2!$E:$E, 0)), ""), "-")
A100: Ann & Elizabeth | B100: John Dunham, 25, slender fellow, (Nathaniel Hannah). Formerly slave to James Dunham of Augusta; left him 5 years past. | C100: Ship Ann & Elizabeth bound for Port Roseway Ben Fowler, Master | D100: John | E100: Dunham | F100: 1758 | G100: 421 | H100: 27 | I100: Book One Part One | J100: Ben Fowler | K100: - | L100: - | M100: - | N100: - | O100: Male | P100: Black | Q100: African American | R100: New York | S100: - | T100: New York | U100: 1783 | V100: Port Roseway | W100: Book of Negroes, British Headquarters Papers PRO 30/55/100; Loyalist evacuation shipping lists (1782–1784) | X100: Book of Negroes | Y100: Nathaniel Hannah | Z100: Black | AA100: - | AB100: - | AC100: Augusta | AD100: United States | AG100: =IF(AD100="United States", IFERROR(INDEX(Sheet2!$C:$C, MATCH(AE100&AF100, Sheet2!$E:$E, 0)) & ", " & INDEX(Sheet2!$D:$D, MATCH(AE100&AF100, Sheet2!$E:$E, 0)), ""), "-")
A101: Antelope | D101: Dan | E101: - | F101: 1776 | G101: 965 | H101: 41 | J101: Gordon | O101: Child Male | R101: New York | T101: New York | U101: 1783 | V101: Bremer Lee | W101: Book of Negroes, British Headquarters Papers PRO 30/55/100; Loyalist evacuation shipping lists (1782–1784) | X101: Book of Negroes | Y101: - | AA101: - | AB101: - | AC101: - | AD101: United States | AG101: =IF(AD101="United States", IFERROR(INDEX(Sheet2!$C:$C, MATCH(AE101&AF101, Sheet2!$E:$E, 0)) & ", " & INDEX(Sheet2!$D:$D, MATCH(AE101&AF101, Sheet2!$E:$E, 0)), ""), "-")
A102: Antelope | D102: George | E102: Bishick | F102: 1757 | G102: 966 | H102: 41 | J102: Gordon | O102: Male | R102: New York | T102: New York | U102: 1783 | V102: Bremer Lee | W102: Book of Negroes, British Headquarters Papers PRO 30/55/100; Loyalist evacuation shipping lists (1782–1784) | X102: Book of Negroes | Y102: - | AA102: - | AB102: - | AC102: - | AD102: United States | AG102: =IF(AD102="United States", IFERROR(INDEX(Sheet2!$C:$C, MATCH(AE102&AF102, Sheet2!$E:$E, 0)) & ", " & INDEX(Sheet2!$D:$D, MATCH(AE102&AF102, Sheet2!$E:$E, 0)), ""), "-")
A103: Antelope Gordon | B103: Dan, 7, likely boy, Kloproth Lt. Anhalt Zerbel of East Friesland, claimant. (Kloproth). Produces a receipt from John Oakes of Oyster Bay of having bought him for seven guineas, who insures him his property. | C103: Antelope Gordon bound for Bremer Lee | D103: Dan | E103: - | F103: 1776 | G103: 882 | H103: - | I103: Book One Part Two | J103: - | K103: - | L103: - | M103: - | N103: - | O103: Child Male | P103: Black | Q103: African American | R103: - | S103: - | T103: - | U103: - | V103: - | W103: - | X103: - | Y103: Kloproth | Z103: Black | AA103: East Friesland | AB103: - | AC103: Oyster Bay | AD103: United States | AG103: =IF(AD103="United States", IFERROR(INDEX(Sheet2!$C:$C, MATCH(AE103&AF103, Sheet2!$E:$E, 0)) & ", " & INDEX(Sheet2!$D:$D, MATCH(AE103&AF103, Sheet2!$E:$E, 0)), ""), "-")
A104: Antelope Gordon | B104: George Bishick, 26, stout fellow. He is Cook on board the ship. Left Virginia 6 years ago. Says he was born free and brought off by a party of marines of the Otter Sloop. | C104: Antelope Gordon bound for Bremer Lee | D104: George | E104: Bishick | F104: 1757 | G104: 883 | H104: - | I104: Book One Part Two | J104: - | K104: - | L104: - | M104: - | N104: - | O104: Male | P104: Black | Q104: African American | R104: - | S104: Virginia | T104: - | U104: - | V104: - | W104: - | X104: - | Y104: - | Z104: Black | AA104: - | AB104: - | AC104: Virginia | AD104: United States | AG104: =IF(AD104="United States", IFERROR(INDEX(Sheet2!$C:$C, MATCH(AE104&AF104, Sheet2!$E:$E, 0)) & ", " & INDEX(Sheet2!$D:$D, MATCH(AE104&AF104, Sheet2!$E:$E, 0)), ""), "-")
A105: Antelope Gordon | B105: Dan, 7, likely boy, Kloproth Lt. Anhalt Zerbel of East Friesland, claimant. (Kloproth). Produces a receipt from John Oakes of Oyster Bay of having bought him for seven guineas, who insures him his property. | C105: Antelope Gordon bound for Bremer Lee | D105: Dan | E105: - | F105: 1776 | G105: 1158 | H105: - | I105: Book One Part Two | J105: - | K105: - | L105: - | M105: - | N105: - | O105: Child Male | P105: Black | Q105: African American | R105: - | S105: - | T105: - | U105: - | V105: - | W105: - | X105: - | Y105: Kloproth | Z105: Black | AA105: East Friesland | AB105: - | AC105: Oyster Bay | AD105: United States | AG105: =IF(AD105="United States", IFERROR(INDEX(Sheet2!$C:$C, MATCH(AE105&AF105, Sheet2!$E:$E, 0)) & ", " & INDEX(Sheet2!$D:$D, MATCH(AE105&AF105, Sheet2!$E:$E, 0)), ""), "-")
A106: Antelope Gordon | B106: George Bishick, 26, stout fellow. He is Cook on board the ship. Left Virginia 6 years ago. Says he was born free and brought off by a party of marines of the Otter Sloop. | C106: Antelope Gordon bound for Bremer Lee | D106: George | E106: Bishick | F106: 1757 | G106: 1159 | H106: - | I106: Book One Part Two | J106: - | K106: - | L106: - | M106: - | N106: - | O106: Male | P106: Black | Q106: African American | R106: - | S106: Virginia | T106: - | U106: - | V106: - | W106: - | X106: - | Y106: - | Z106: Black | AA106: - | AB106: - | AC106: Virginia | AD106: United States | AG106: =IF(AD106="United States", IFERROR(INDEX(Sheet2!$C:$C, MATCH(AE106&AF106, Sheet2!$E:$E, 0)) & ", " & INDEX(Sheet2!$D:$D, MATCH(AE106&AF106, Sheet2!$E:$E, 0)), ""), "-")
A107: Apollo | B107: James Jackson, 12, stout boy, (Edward Green). Produced a Certificate from Benjamin James that he is free, both indented to Edward Green till they are 21 to learn the trade of Shoemaker. | C107: Apollo bound for Port Roseway John Adamson | D107: James | E107: Jackson | F107: 1771 | G107: 823 | H107: 30 | I107: Book One Part One | J107: John Adamson | K107: - | L107: - | M107: - | N107: - | O107: Child Male | P107: Black | Q107: African American | R107: New York | S107: - | T107: New York | U107: 8 Jun 1783 | V107: Port Roseway | W107: Book of Negroes, British Headquarters Papers PRO 30/55/100; Loyalist evacuation shipping lists (1782–1784) | X107: Loyalist evacuation lists | Y107: Edward Green | Z107: Black | AA107: - | AB107: - | AC107: Shoemaker | AD107: United States | AG107: =IF(AD107="United States", IFERROR(INDEX(Sheet2!$C:$C, MATCH(AE107&AF107, Sheet2!$E:$E, 0)) & ", " & INDEX(Sheet2!$D:$D, MATCH(AE107&AF107, Sheet2!$E:$E, 0)), ""), "-")
A108: Apollo | B108: Bob, 15, likely boy, (Adj. Cunningham. His property. | C108: Apollo bound for St. John's | D108: Bob | E108: - | F108: 1768 | G108: 1969 | H108: - | I108: Book One Part Two | J108: - | K108: - | L108: - | M108: - | N108: - | O108: Child Male | P108: Black | Q108: African American | R108: - | S108: - | T108: - | U108: - | V108: St. John's | W108: - | X108: - | Y108: - | Z108: Black | AA108: - | AB108: - | AC108: - | AD108: United States | AG108: =IF(AD108="United States", IFERROR(INDEX(Sheet2!$C:$C, MATCH(AE108&AF108, Sheet2!$E:$E, 0)) & ", " & INDEX(Sheet2!$D:$D, MATCH(AE108&AF108, Sheet2!$E:$E, 0)), ""), "-")
A109: Apollo | B109: Jupiter Wise, 25, stout fellow, B, (Henry Hotchinson). Certified to be free by the Commandant. | C109: Apollo bound for Port Roseway John Adamson | D109: Jupiter | E109: Wise | F109: 1758 | G109: 774 | H109: - | I109: Book One Part One | J109: John Adamson | K109: - | L109: - | M109: - | N109: - | O109: Male | P109: Black | Q109: African American | R109: - | S109: - | T109: - | U109: - | V109: Port Roseway | W109: - | X109: - | Y109: Henry Hotchinson | Z109: Black | AA109: - | AB109: - | AC109: - | AD109: United States | AG109: =IF(AD109="United States", IFERROR(INDEX(Sheet2!$C:$C, MATCH(AE109&AF109, Sheet2!$E:$E, 0)) & ", " & INDEX(Sheet2!$D:$D, MATCH(AE109&AF109, Sheet2!$E:$E, 0)), ""), "-")
A110: Apollo | B110: Jeff, 12, likely boy, (Lieut. B. Ward). His own property. | C110: Apollo bound for St. John's | D110: Jeff | E110: - | F110: 1771 | G110: 1970 | H110: - | I110: Book One Part Two | J110: - | K110: - | L110: - | M110: - | N110: - | O110: Child Male | P110: Black | Q110: African American | R110: - | S110: - | T110: - | U110: - | V110: St. John's | W110: - | X110: - | Y110: Lieut. B. Ward | Z110: Black | AA110: - | AB110: - | AC110: - | AD110: United States | AG110: =IF(AD110="United States", IFERROR(INDEX(Sheet2!$C:$C, MATCH(AE110&AF110, Sheet2!$E:$E, 0)) & ", " & INDEX(Sheet2!$D:$D, MATCH(AE110&AF110, Sheet2!$E:$E, 0)), ""), "-")
A111: Apollo | B111: Vinia, 25, stout wench, M, (Capt. Willmot). Capt. Willmot's property. | C111: Apollo bound for St. John's | D111: Vinia | E111: - | F111: 1758 | G111: 1971 | H111: 62 | I111: Book One Part Two | J111: - | K111: - | L111: - | M111: - | N111: - | O111: Female | P111: Black | Q111: African American | R111: New York | S111: - | T111: New York | U111: 8 Jun 1783 | V111: St. John's | W111: Book of Negroes, British Headquarters Papers PRO 30/55/100; Loyalist evacuation shipping lists (1782–1784) | X111: Loyalist evacuation lists | Y111: Capt. Willmot | Z111: Black | AA111: - | AB111: - | AC111: - | AD111: United States | AG111: =IF(AD111="United States", IFERROR(INDEX(Sheet2!$C:$C, MATCH(AE111&AF111, Sheet2!$E:$E, 0)) & ", " & INDEX(Sheet2!$D:$D, MATCH(AE111&AF111, Sheet2!$E:$E, 0)), ""), "-")
A112: Apollo | B112: Cara Wilkins, 27, stout wench, M, (Lewis Palmer). Formerly slave to John Wilkinson, New Jersey; left him in the year 1776. | C112: Apollo bound for Port Roseway John Adamson | D112: Cara | E112: Wilkins | F112: 1756 | G112: 773 | H112: - | I112: Book One Part One | J112: John Adamson | K112: - | L112: - | M112: - | N112: - | O112: Female | P112: Black | Q112: African American | R112: Formerly slave to John Wilkinson | S112: New Jersey | T112: - | U112: - | V112: Port Roseway | W112: - | X112: - | Y112: Lewis Palmer | Z112: Black | AA112: - | AB112: - | AC112: New Jersey | AD112: United States | AG112: =IF(AD112="United States", IFERROR(INDEX(Sheet2!$C:$C, MATCH(AE112&AF112, Sheet2!$E:$E, 0)) & ", " & INDEX(Sheet2!$D:$D, MATCH(AE112&AF112, Sheet2!$E:$E, 0)), ""), "-")
A113: Apollo | B113: Edward Jackson, 14, stout boy, (Edward Green). Produced a Certificate from Benjamin James that he is free. | C113: Apollo bound for Port Roseway John Adamson | D113: Edward | E113: Jackson | F113: 1769 | G113: 822 | H113: 39 | I113: Book One Part One | J113: John Adamson | K113: - | L113: - | M113: - | N113: - | O113: Child Male | P113: Black | Q113: African American | R113: New York | S113: - | T113: New York | U113: 8 Jun 1783 | V113: Port Roseway | W113: Book of Negroes, British Headquarters Papers PRO 30/55/100; Loyalist evacuation shipping lists (1782–1784) | X113: Loyalist evacuation lists | Y113: Edward Green | Z113: Black | AA113: - | AB113: - | AC113: - | AD113: United States | AG113: =IF(AD113="United States", IFERROR(INDEX(Sheet2!$C:$C, MATCH(AE113&AF113, Sheet2!$E:$E, 0)) & ", " & INDEX(Sheet2!$D:$D, MATCH(AE113&AF113, Sheet2!$E:$E, 0)), ""), "-")
A114: Apollo | B114: Dinah, 26, stout wench, M. Robert Wilkins of Port Roseway, claimant. (Robert Wilkins). His property having produced a Bill of Sale. | C114: Apollo bound for Port Roseway John Adamson | D114: Dinah | E114: - | F114: 1757 | G114: 825 | H114: 39 | I114: Book One Part One | J114: John Adamson | K114: - | L114: - | M114: - | N114: - | O114: Female | P114: Black | Q114: African American | R114: New York | S114: - | T114: New York | U114: 8 Jun 1783 | V114: Port Roseway | W114: Book of Negroes, British Headquarters Papers PRO 30/55/100; Loyalist evacuation shipping lists (1782–1784) | X114: Loyalist evacuation lists | Y114: Robert Wilkins | Z114: Black | AA114: - | AB114: - | AC114: - | AD114: United States | AG114: =IF(AD114="United States", IFERROR(INDEX(Sheet2!$C:$C, MATCH(AE114&AF114, Sheet2!$E:$E, 0)) & ", " & INDEX(Sheet2!$D:$D, MATCH(AE114&AF114, Sheet2!$E:$E, 0)), ""), "-")
A115: Apollo | B115: Sally Bowden, 27, ordinary wench, B. | C115: Apollo bound for Port Roseway John Adamson | D115: Sally | E115: Bowden | F115: 1756 | G115: 776 | H115: - | I115: Book One Part One | J115: John Adamson | K115: - | L115: - | M115: - | N115: - | O115: Female | P115: Black | Q115: African American | R115: - | S115: - | T115: - | U115: - | V115: Port Roseway | W115: - | X115: - | Y115: - | Z115: Black | AA115: - | AB115: - | AC115: - | AD115: United States | AG115: =IF(AD115="United States", IFERROR(INDEX(Sheet2!$C:$C, MATCH(AE115&AF115, Sheet2!$E:$E, 0)) & ", " & INDEX(Sheet2!$D:$D, MATCH(AE115&AF115, Sheet2!$E:$E, 0)), ""), "-")
A116: Apollo | D116: Roger their | E116: son | F116: 1769 | G116: 598 | H116: 30 | J116: John Adams | O116: Child Male | R116: New York | T116: New York | U116: 8 Jun 1783 | V116: Port Roseway | W116: Book of Negroes, British Headquarters Papers PRO 30/55/100; Loyalist evacuation shipping lists (1782–1784) | X116: Loyalist evacuation lists | Y116: - | AA116: - | AB116: - | AC116: - | AD116: United States | AG116: =IF(AD116="United States", IFERROR(INDEX(Sheet2!$C:$C, MATCH(AE116&AF116, Sheet2!$E:$E, 0)) & ", " & INDEX(Sheet2!$D:$D, MATCH(AE116&AF116, Sheet2!$E:$E, 0)), ""), "-")
A117: Apollo | D117: Freelove his | E117: wife | F117: 1734 | G117: 597 | H117: 30 | J117: John Adams | O117: Female | R117: New York | T117: New York | U117: 8 Jun 1783 | V117: Port Roseway | W117: Book of Negroes, British Headquarters Papers PRO 30/55/100; Loyalist evacuation shipping lists (1782–1784) | X117: Loyalist evacuation lists | Y117: - | AA117: - | AB117: - | AC117: - | AD117: United States | AG117: =IF(AD117="United States", IFERROR(INDEX(Sheet2!$C:$C, MATCH(AE117&AF117, Sheet2!$E:$E, 0)) & ", " & INDEX(Sheet2!$D:$D, MATCH(AE117&AF117, Sheet2!$E:$E, 0)), ""), "-")
A118: Apollo | B118: Thomas Rogers, 40, ordinary fellow, B, (Lewis Palmer). Formerly slave to Thomas Wollerd, Chester County, Pennsylvania; left him about 5 years ago. | C118: Apollo bound for Port Roseway John Adamson | D118: Thomas | E118: Rogers | F118: 1743 | G118: 772 | H118: - | I118: Book One Part One | J118: John Adamson | K118: - | L118: - | M118: - | N118: - | O118: Male | P118: Black | Q118: African American | R118: Chester County | S118: Pennsylvania | T118: - | U118: - | V118: Port Roseway | W118: - | X118: - | Y118: Lewis Palmer | Z118: Black | AA118: Chester County | AB118: - | AC118: Pennsylvania | AD118: United States | AG118: =IF(AD118="United States", IFERROR(INDEX(Sheet2!$C:$C, MATCH(AE118&AF118, Sheet2!$E:$E, 0)) & ", " & INDEX(Sheet2!$D:$D, MATCH(AE118&AF118, Sheet2!$E:$E, 0)), ""), "-")
A119: Apollo | B119: Robert, her Vinia's infant, (Capt. Willmot). Capt Willmot's property. | C119: Apollo bound for St. John's | D119: Robert | F119: - | G119: 2720 | I119: Book One Part Two | J119: - | O119: Male | P119: Black | Q119: African American | V119: St. John's | Y119: Capt. Willmot | Z119: Black | AA119: - | AB119: - | AC119: - | AD119: United States | AG119: =IF(AD119="United States", IFERROR(INDEX(Sheet2!$C:$C, MATCH(AE119&AF119, Sheet2!$E:$E, 0)) & ", " & INDEX(Sheet2!$D:$D, MATCH(AE119&AF119, Sheet2!$E:$E, 0)), ""), "-")
A120: Apollo | B120: Harry, her Vinia's infant, (Capt. Willmot). Capt. Willmot's property. | C120: Apollo bound for St. John's | D120: Harry | F120: - | G120: 2719 | I120: Book One Part Two | J120: - | O120: Male | P120: Black | Q120: African American | V120: St. John's | Y120: Capt. Willmot | Z120: Black | AA120: - | AB120: - | AC120: - | AD120: United States | AG120: =IF(AD120="United States", IFERROR(INDEX(Sheet2!$C:$C, MATCH(AE120&AF120, Sheet2!$E:$E, 0)) & ", " & INDEX(Sheet2!$D:$D, MATCH(AE120&AF120, Sheet2!$E:$E, 0)), ""), "-")
A121: Apollo | B121: Jack Rogers, 50, stout man, (John Libby). Left free by his master, James Rogers, Newport, Rhode Island, who died 5 years before the war. | C121: Ship Apollo bound for Port Roseway John Adams | D121: Jack | E121: Rogers | F121: 1733 | G121: 2696 | I121: Book One Part One | J121: John Adams | O121: Male | P121: Black | Q121: African American | V121: Port Roseway | Y121: John Libby | Z121: Black | AA121: Newport | AB121: - | AC121: Rhode Island | AD121: United States | AG121: =IF(AD121="United States", IFERROR(INDEX(Sheet2!$C:$C, MATCH(AE121&AF121, Sheet2!$E:$E, 0)) & ", " & INDEX(Sheet2!$D:$D, MATCH(AE121&AF121, Sheet2!$E:$E, 0)), ""), "-")
A122: Apollo | B122: Dempsey Bowden, 2 months, M. | C122: Apollo bound for Port Roseway John Adamson | D122: Dempsey | E122: Bowden | F122: 1781 | G122: 777 | H122: - | I122: Book One Part One | J122: John Adamson | K122: - | L122: - | M122: - | N122: - | O122: Child Male | P122: Black | Q122: African American | R122: - | S122: - | T122: - | U122: - | V122: Port Roseway | W122: - | X122: - | Y122: - | Z122: Black | AA122: - | AB122: - | AC122: - | AD122: United States | AG122: =IF(AD122="United States", IFERROR(INDEX(Sheet2!$C:$C, MATCH(AE122&AF122, Sheet2!$E:$E, 0)) & ", " & INDEX(Sheet2!$D:$D, MATCH(AE122&AF122, Sheet2!$E:$E, 0)), ""), "-")
A123: Apollo | D123: Silvia his | E123: wife | F123: 1747 | G123: 602 | H123: 30 | J123: John Adams | O123: Female | R123: New York | T123: New York | U123: 8 Jun 1783 | V123: Port Roseway | W123: Book of Negroes, British Headquarters Papers PRO 30/55/100; Loyalist evacuation shipping lists (1782–1784) | X123: Loyalist evacuation lists | Y123: - | AA123: - | AB123: - | AC123: - | AD123: United States | AG123: =IF(AD123="United States", IFERROR(INDEX(Sheet2!$C:$C, MATCH(AE123&AF123, Sheet2!$E:$E, 0)) & ", " & INDEX(Sheet2!$D:$D, MATCH(AE123&AF123, Sheet2!$E:$E, 0)), ""), "-")
A124: Apollo | B124: Henry Carter, 24, stout fellow, (Edward Green). Formerly slave to William Elliot of Middlesex, Virginia; left him 3 years ago. GBC. | C124: Apollo bound for Port Roseway John Adamson | D124: Henry | E124: Carter | F124: 1759 | G124: 824 | H124: 39 | I124: Book One Part One | J124: John Adamson | K124: - | L124: - | M124: - | N124: - | O124: Male | P124: Black | Q124: African American | R124: New York | S124: Virginia | T124: New York | U124: 8 Jun 1783 | V124: Port Roseway | W124: Book of Negroes, British Headquarters Papers PRO 30/55/100; Loyalist evacuation shipping lists (1782–1784) | X124: Loyalist evacuation lists | Y124: Edward Green | Z124: Black | AA124: Middlesex | AB124: - | AC124: Virginia | AD124: United States | AG124: =IF(AD124="United States", IFERROR(INDEX(Sheet2!$C:$C, MATCH(AE124&AF124, Sheet2!$E:$E, 0)) & ", " & INDEX(Sheet2!$D:$D, MATCH(AE124&AF124, Sheet2!$E:$E, 0)), ""), "-")
...

Sheet Sheet2
A1: County | B1: State | C1: lat | D1: lng | E1: LookupKey | J1: AK
A2: Aleutians East | B2: AK | C2: 55.3669 | D2: -161.9805 | E2: AKAleutians East | J2: AL
A3: Aleutians West | B3: AK | C3: 52.7985 | D3: -106.5633 | E3: AKAleutians West | J3: AR
A4: Anchorage | B4: AK | C4: 61.1498 | D4: -149.1082 | E4: AKAnchorage | J4: AZ
A5: Bethel | B5: AK | C5: 60.9132 | D5: -159.8186 | E5: AKBethel | J5: CA
A6: Bristol Bay | B6: AK | C6: 58.7431 | D6: -156.7015 | E6: AKBristol Bay | J6: CO
A7: Chugach | B7: AK | C7: 60.7233 | D7: -145.7583 | E7: AKChugach | J7: CT
A8: Copper River | B8: AK | C8: 61.8855 | D8: -143.97 | E8: AKCopper River | J8: DC
A9: Denali | B9: AK | C9: 63.6714 | D9: -150.0118 | E9: AKDenali | J9: DE
A10: Dillingham | B10: AK | C10: 59.8003 | D10: -158.2346 | E10: AKDillingham | J10: FL
A11: Fairbanks North Star | B11: AK | C11: 64.8078 | D11: -146.5654 | E11: AKFairbanks North Star | J11: GA
A12: Haines | B12: AK | C12: 59.1186 | D12: -135.5007 | E12: AKHaines | J12: HI
A13: Hoonah-Angoon | B13: AK | C13: 58.287 | D13: -135.6393 | E13: AKHoonah-Angoon | J13: IA
... A51: Covington | B51: AL | C51: 31.2485 | D51: -86.4513 | E51: ALCovington | J51: WY
A52: Crenshaw | B52: AL | C52: 31.7315 | D52: -86.3136 | E52: ALCrenshaw
A53: Cullman | B53: AL | C53: 34.1319 | D53: -86.8676 | E53: ALCullman
A54: Dale | B54: AL | C54: 31.4318 | D54: -85.611 | E54: ALDale
A55: Dallas | B55: AL | C55: 32.326 | D55: -87.1065 | E55: ALDallas
A56: DeKalb | B56: AL | C56: 34.4598 | D56: -85.8041 | E56: ALDeKalb
A57: Elmore | B57: AL | C57: 32.5966 | D57: -86.1492 | E57: ALElmore
A58: Escambia | B58: AL | C58: 31.1261 | D58: -87.1615 | E58: ALEscambia
A59: Etowah | B59: AL | C59: 34.0453 | D59: -86.0348 | E59: ALEtowah
A60: Fayette | B60: AL | C60: 33.7212 | D60: -87.7388 | E60: ALFayette
A61: Franklin | B61: AL | C61: 34.4417 | D61: -87.8437 | E61: ALFranklin
A62: Geneva | B62: AL | C62: 31.095 | D62: -85.8391 | E62: ALGeneva
A63: Greene | B63: AL | C63: 32.8531 | D63: -87.9522 | E63: ALGreene
... A3145: Weston | B3145: WY | C3145: 43.8404 | D3145: -104.5677 | E3145: WYWeston
