Workbook

Sheet Main
A1: First_Name | B1: Surname | C1: Father_FirstName | D1: Father_Surname | E1: Mother_FirstName | F1: Mother_Surname | G1: Gender | H1: Age | I1: Birthdate | J1: Race | K1: Ethnicity | L1: Origin | M1: Extracted_City | N1: Extracted_County | O1: Extracted_State | P1: State | Q1: County | R1: Coordinates | S1: Origination_Port | T1: Origination_State | U1: Departure_Port | V1: Departure_Date | W1: Arrival_Port_City | X1: Arrival_County | Y1: Arrival_State | Z1: Primary_Source_1 | AA1: Primary_Source_2 | AB1: Notes | AC1: Country | AD1: ID | AE1: Ref_Page | AF1: Book | AG1: Ship_Name | AH1: Commander | AI1: Ship_Notes
A2: William | B2: Johnson | C2: - | D2: - | E2: - | F2: - | G2: Male | H2: 21 | I2: 1762 | J2: Black | K2: African American | L2: Black | M2: Ann County | N2: - | O2: Virginia | R2: =IFERROR(INDEX(Sheet2!$C:$C, MATCH(P2&Q2, Sheet2!$E:$E, 0)) & ", " & INDEX(Sheet2!$D:$D, MATCH(P2&Q2, Sheet2!$E:$E, 0)), "-") -> - | S2: Formerly slave to John Chapman of Princess Ann County | T2: Virginia | U2: - | V2: - | W2: River St. John's | Y2: Canada | Z2: - | AA2: - | AB2: William Johnson, 21, stout likely fellow, (Lt. Richard Holland). Formerly slave to John Chapman of Princess Ann County, Virginia; left him 4 years. | AD2: 744 | AE2: - | AF2: Book One Part One | AG2: 3 Friends | AH2: John Stewart | AI2: Sloop 3 Friends bound for River St. John's John Stewart, Master
A3: Sally | B3: her child | C3: - | D3: - | E3: Elizabeth | F3: Merrick | G3: Child Male | H3: 8 | I3: 1775 | J3: Black | K3: African American | L3: Black | M3: - | N3: - | O3: - | R3: =IFERROR(INDEX(Sheet2!$C:$C, MATCH(P3&Q3, Sheet2!$E:$E, 0)) & ", " & INDEX(Sheet2!$D:$D, MATCH(P3&Q3, Sheet2!$E:$E, 0)), "-") -> - | S3: - | T3: - | U3: - | V3: - | W3: River St. John's | Y3: Canada | Z3: - | AA3: - | AB3: Sally her child, 8 mo. | AD3: 746 | AE3: - | AF3: Book One Part One | AG3: 3 Friends | AH3: John Stewart | AI3: Sloop 3 Friends bound for River St. John's John Stewart, Master
A4: Elizabeth | B4: Merrick | C4: - | D4: - | E4: - | F4: - | G4: Female | H4: 27 | I4: 1756 | J4: Black | K4: African American | L4: Black | M4: Newtown | N4: - | O4: Long Island | R4: =IFERROR(INDEX(Sheet2!$C:$C, MATCH(P4&Q4, Sheet2!$E:$E, 0)) & ", " & INDEX(Sheet2!$D:$D, MATCH(P4&Q4, Sheet2!$E:$E, 0)), "-") -> - | S4: - | T4: - | U4: - | V4: - | W4: River St. John's | Y4: Canada | Z4: - | AA4: - | AB4: Elizabeth Merrick, 27, stout wench, M, (Luther Hatheway). Born free; served her time with Lambert Woodward of Newtown, Long Island. | AD4: 743 | AE4: - | AF4: Book One Part One | AG4: 3 Friends | AH4: John Stewart | AI4: Sloop 3 Friends bound for River St. John's John Stewart, Master
A5: Richard | B5: Merrick | C5: Tom | D5: Gunn | E5: - | F5: - | G5: Male | H5: 32 | I5: 1751 | J5: Black | K5: African American | L5: Black | M5: Springfield | N5: - | O5: Massachusetts | R5: =IFERROR(INDEX(Sheet2!$C:$C, MATCH(P5&Q5, Sheet2!$E:$E, 0)) & ", " & INDEX(Sheet2!$D:$D, MATCH(P5&Q5, Sheet2!$E:$E, 0)), "-") -> - | S5: - | T5: - | U5: - | V5: - | W5: River St. John's | Y5: Canada | Z5: - | AA5: - | AB5: Richard Merrick, 32, stout likely fellow, (Sam Wilson). Formerly slave to Samuel Merrick of Springfield, Massachusetts, who gave him his freedom & produced a Certificate dated 4 November 74, signed by Merrick, Philips & Dr. White. | AD5: 742 | AE5: - | AF5: Book One Part One | AG5: 3 Friends | AH5: John Stewart | AI5: Sloop 3 Friends bound for River St. John's John Stewart, Master
A6: Tom | B6: Gunn | C6: - | D6: - | E6: - | F6: - | G6: Male | H6: 43 | I6: 1740 | J6: Black | K6: African American | L6: Black | M6: Waterbury | N6: - | O6: Connecticut | R6: =IFERROR(INDEX(Sheet2!$C:$C, MATCH(P6&Q6, Sheet2!$E:$E, 0)) & ", " & INDEX(Sheet2!$D:$D, MATCH(P6&Q6, Sheet2!$E:$E, 0)), "-") -> - | S6: - | T6: - | U6: - | V6: - | W6: River St. John's | Y6: Canada | Z6: - | AA6: - | AB6: Tom Gunn, 43, stout, pockmarked, (Sam Wilson). Formerly slave to Enos Gunn of Waterbury, Connecticut. | AD6: 741 | AE6: - | AF6: Book One Part One | AG6: 3 Friends | AH6: John Stewart | AI6: Sloop 3 Friends bound for River St. John's John Stewart, Master
A7: Hannah | B7: and | C7: - | D7: - | E7: - | F7: - | G7: Child Female | H7: 16 | I7: 1767 | J7: Black | K7: African American | L7: Black | M7: - | N7: - | O7: Long Island | R7: =IFERROR(INDEX(Sheet2!$C:$C, MATCH(P7&Q7, Sheet2!$E:$E, 0)) & ", " & INDEX(Sheet2!$D:$D, MATCH(P7&Q7, Sheet2!$E:$E, 0)), "-") -> - | S7: - | T7: - | U7: - | V7: - | W7: River St. John's | Y7: Canada | Z7: - | AA7: - | AB7: Hannah and, 16, stout wench, (Lt. Richard Holland). Born free in Cow Neck, Long Island, lived with Caleb Merrill till within this last year. | AD7: 745 | AE7: - | AF7: Book One Part One | AG7: 3 Friends | AH7: John Stewart | AI7: Sloop 3 Friends bound for River St. John's John Stewart, Master
A8: 18 | B8: September | G8: Male | H8: 18 | I8: 1765 | J8: Black | K8: African American | L8: Black | M8: - | N8: - | O8: - | R8: =IFERROR(INDEX(Sheet2!$C:$C, MATCH(P8&Q8, Sheet2!$E:$E, 0)) & ", " & INDEX(Sheet2!$D:$D, MATCH(P8&Q8, Sheet2!$E:$E, 0)), "-") -> - | W8: Quebec John Wardell | Y8: Canada | AB8: 18 September | AD8: 2716 | AF8: Book One Part Two | AG8: 3 Sisters | AH8: - | AI8: 3 Sisters bound for Quebec John Wardell
A9: Cairo | B9: - | C9: - | D9: - | E9: - | F9: - | G9: Female | H9: 20 | I9: 1763 | J9: Black | K9: African American | L9: Black | M9: - | N9: - | O9: Cairo | R9: =IFERROR(INDEX(Sheet2!$C:$C, MATCH(P9&Q9, Sheet2!$E:$E, 0)) & ", " & INDEX(Sheet2!$D:$D, MATCH(P9&Q9, Sheet2!$E:$E, 0)), "-") -> - | S9: New York | T9: - | U9: New York | V9: Fall 1783 | W9: St. John's | Y9: Canada | Z9: Book of Negroes, British Headquarters Papers PRO 30/55/100; Loyalist evacuation shipping lists (1782–1784) | AA9: Loyalist evacuation lists | AB9: Cairo, 20, stout wench, (James Peters). Property of James Petes. | AD9: 2254 | AE9: 70 | AF9: Book Two | AG9: Alexander | AH9: Roger Alderson | AI9: Alexander bound for St. John's Roger Alderson
A10: Bella | B10: - | C10: - | D10: - | E10: - | F10: - | G10: Child Female | H10: 14 | I10: 1769 | J10: Black | K10: African American | L10: Black | M10: - | N10: - | O10: - | R10: =IFERROR(INDEX(Sheet2!$C:$C, MATCH(P10&Q10, Sheet2!$E:$E, 0)) & ", " & INDEX(Sheet2!$D:$D, MATCH(P10&Q10, Sheet2!$E:$E, 0)), "-") -> - | S10: New York | T10: - | U10: New York | V10: Fall 1783 | W10: St. John's | Y10: Canada | Z10: Book of Negroes, British Headquarters Papers PRO 30/55/100; Loyalist evacuation shipping lists (1782–1784) | AA10: Loyalist evacuation lists | AB10: Bella, 14, stout wench, (James Peters). Property of James Peters. | AD10: 2255 | AE10: 70 | AF10: Book Two | AG10: Alexander | AH10: Roger Alderson | AI10: Alexander bound for St. John's Roger Alderson
A11: Esther | B11: - | C11: - | D11: - | E11: - | F11: - | G11: Female | H11: 18 | I11: 1765 | J11: Black | K11: African American | L11: Black | M11: - | N11: - | O11: Esther | R11: =IFERROR(INDEX(Sheet2!$C:$C, MATCH(P11&Q11, Sheet2!$E:$E, 0)) & ", " & INDEX(Sheet2!$D:$D, MATCH(P11&Q11, Sheet2!$E:$E, 0)), "-") -> - | S11: New York | T11: - | U11: New York | V11: Fall 1783 | W11: St. John's | Y11: Canada | Z11: Book of Negroes, British Headquarters Papers PRO 30/55/100; Loyalist evacuation shipping lists (1782–1784) | AA11: Loyalist evacuation lists | AB11: Esther, 18, stout wench, M, (Bartholomew Cranell). Property of Bartholomew Crannell. | AD11: 2256 | AE11: 70 | AF11: Book Two | AG11: Alexander | AH11: Roger Alderson | AI11: Alexander bound for St. John's Roger Alderson
A12: Robert | B12: - | C12: - | D12: - | E12: - | F12: - | G12: Male | H12: 36 | I12: 1747 | J12: Black | K12: African American | L12: Black | M12: - | N12: - | O12: - | R12: =IFERROR(INDEX(Sheet2!$C:$C, MATCH(P12&Q12, Sheet2!$E:$E, 0)) & ", " & INDEX(Sheet2!$D:$D, MATCH(P12&Q12, Sheet2!$E:$E, 0)), "-") -> - | S12: New York | T12: - | U12: New York | V12: Fall 1783 | W12: St. John's | Y12: Canada | Z12: Book of Negroes, British Headquarters Papers PRO 30/55/100; Loyalist evacuation shipping lists (1782–1784) | AA12: Loyalist evacuation lists | AB12: Robert, 36, stout fellow, (Bartholomew Crannell). Formerly slave to Isaac Conklin, 9 Partners; left him 2 years ago. | AD12: 2258 | AE12: 70 | AF12: Book Two | AG12: Alexander | AH12: Roger Alderson | AI12: Alexander bound for St. John's Roger Alderson
A13: Pompey | B13: - | C13: - | D13: - | E13: - | F13: - | G13: Male | H13: 25 | I13: 1758 | J13: Black | K13: African American | L13: Black | M13: - | N13: - | O13: - | R13: =IFERROR(INDEX(Sheet2!$C:$C, MATCH(P13&Q13, Sheet2!$E:$E, 0)) & ", " & INDEX(Sheet2!$D:$D, MATCH(P13&Q13, Sheet2!$E:$E, 0)), "-") -> - | S13: New York | T13: - | U13: New York | V13: Fall 1783 | W13: St. John's | Y13: Canada | Z13: Book of Negroes, British Headquarters Papers PRO 30/55/100; Loyalist evacuation shipping lists (1782–1784) | AA13: Loyalist evacuation lists | AB13: Pompey, 25, stout fellow, on his own bottom. Born free. | AD13: 2259 | AE13: 70 | AF13: Book Two | AG13: Alexander | AH13: Roger Alderson | AI13: Alexander bound for St. John's Roger Alderson
A14: Sam | B14: - | C14: - | D14: - | E14: - | F14: - | G14: Male | H14: 35 | I14: 1748 | J14: Black | K14: African American | L14: Black | M14: - | N14: - | O14: - | R14: =IFERROR(INDEX(Sheet2!$C:$C, MATCH(P14&Q14, Sheet2!$E:$E, 0)) & ", " & INDEX(Sheet2!$D:$D, MATCH(P14&Q14, Sheet2!$E:$E, 0)), "-") -> - | S14: New York | T14: - | U14: New York | V14: Fall 1783 | W14: St. John's | Y14: Canada | Z14: Book of Negroes, British Headquarters Papers PRO 30/55/100; Loyalist evacuation shipping lists (1782–1784) | AA14: Loyalist evacuation lists | AB14: Sam, 35, (Bartholomew Cranell). Property of Bartholomew Crannell. | AD14: 2257 | AE14: 70 | AF14: Book Two | AG14: Alexander | AH14: Roger Alderson | AI14: Alexander bound for St. John's Roger Alderson
A15: Job | B15: State | G15: Male | H15: 24 | I15: 1759 | M15: - | N15: - | O15: - | R15: =IFERROR(INDEX(Sheet2!$C:$C, MATCH(P15&Q15, Sheet2!$E:$E, 0)) & ", " & INDEX(Sheet2!$D:$D, MATCH(P15&Q15, Sheet2!$E:$E, 0)), "-") -> - | S15: New York | U15: New York | V15: 16 Jun 1783 | W15: St. Johns | Y15: Canada | Z15: Book of Negroes, British Headquarters Papers PRO 30/55/100; Loyalist evacuation shipping lists (1782–1784) | AA15: Loyalist evacuation lists | AD15: 742 | AE15: 35 | AG15: Amities Production | AH15: Thomas Reid
A16: William | B16: Holchapan | G16: Male | H16: 40 | I16: 1743 | M16: - | N16: - | O16: - | R16: =IFERROR(INDEX(Sheet2!$C:$C, MATCH(P16&Q16, Sheet2!$E:$E, 0)) & ", " & INDEX(Sheet2!$D:$D, MATCH(P16&Q16, Sheet2!$E:$E, 0)), "-") -> - | S16: New York | U16: New York | V16: 16 Jun 1783 | W16: St. Johns | Y16: Canada | Z16: Book of Negroes, British Headquarters Papers PRO 30/55/100; Loyalist evacuation shipping lists (1782–1784) | AA16: Loyalist evacuation lists | AD16: 743 | AE16: 35 | AG16: Amities Production | AH16: Thomas Reid
A17: George | B17: State | G17: Male | H17: 25 | I17: 1758 | M17: - | N17: - | O17: - | R17: =IFERROR(INDEX(Sheet2!$C:$C, MATCH(P17&Q17, Sheet2!$E:$E, 0)) & ", " & INDEX(Sheet2!$D:$D, MATCH(P17&Q17, Sheet2!$E:$E, 0)), "-") -> - | S17: New York | U17: New York | V17: 16 Jun 1783 | W17: St. Johns | Y17: Canada | Z17: Book of Negroes, British Headquarters Papers PRO 30/55/100; Loyalist evacuation shipping lists (1782–1784) | AA17: Loyalist evacuation lists | AD17: 740 | AE17: 35 | AG17: Amities Production | AH17: Thomas Reid
A18: Mary | B18: State | G18: Female | H18: 21 | I18: 1762 | M18: - | N18: - | O18: - | R18: =IFERROR(INDEX(Sheet2!$C:$C, MATCH(P18&Q18, Sheet2!$E:$E, 0)) & ", " & INDEX(Sheet2!$D:$D, MATCH(P18&Q18, Sheet2!$E:$E, 0)), "-") -> - | S18: New York | U18: New York | V18: 16 Jun 1783 | W18: St. Johns | Y18: Canada | Z18: Book of Negroes, British Headquarters Papers PRO 30/55/100; Loyalist evacuation shipping lists (1782–1784) | AA18: Loyalist evacuation lists | AD18: 741 | AE18: 35 | AG18: Amities Production | AH18: Thomas Reid
A19: William | B19: Stepney | G19: Male | H19: 24 | I19: 1759 | M19: - | N19: - | O19: - | R19: =IFERROR(INDEX(Sheet2!$C:$C, MATCH(P19&Q19, Sheet2!$E:$E, 0)) & ", " & INDEX(Sheet2!$D:$D, MATCH(P19&Q19, Sheet2!$E:$E, 0)), "-") -> - | S19: New York | U19: New York | V19: 16 Jun 1783 | W19: St. Johns | Y19: Canada | Z19: Book of Negroes, British Headquarters Papers PRO 30/55/100; Loyalist evacuation shipping lists (1782–1784) | AA19: Loyalist evacuation lists | AD19: 739 | AE19: 35 | AG19: Amities Production | AH19: Thomas Reid
A20: William | B20: Holchapan | C20: - | D20: - | E20: - | F20: - | G20: Male | H20: 40 | I20: 1743 | J20: Black | K20: African American | L20: Black | M20: St. Paul's | N20: - | O20: London | R20: =IFERROR(INDEX(Sheet2!$C:$C, MATCH(P20&Q20, Sheet2!$E:$E, 0)) & ", " & INDEX(Sheet2!$D:$D, MATCH(P20&Q20, Sheet2!$E:$E, 0)), "-") -> - | S20: - | T20: - | U20: - | V20: - | W20: St. John's | Y20: Canada | Z20: - | AA20: - | AB20: William Holchapan, 40, stout fellow, M, (on his own bottom). Born free and baptized in the year 1779 in the Parish of St. Paul's, London. | AD20: 678 | AE20: - | AF20: Book One Part One | AG20: Amity's Production | AH20: Thomas Reid | AI20: Amity's Production bound for St. John's Thomas Reid, Master
A21: Job | B21: State | C21: - | D21: - | E21: - | F21: - | G21: Male | H21: 24 | I21: 1759 | J21: Black | K21: African American | L21: Black | M21: - | N21: - | O21: New York | R21: =IFERROR(INDEX(Sheet2!$C:$C, MATCH(P21&Q21, Sheet2!$E:$E, 0)) & ", " & INDEX(Sheet2!$D:$D, MATCH(P21&Q21, Sheet2!$E:$E, 0)), "-") -> - | S21: - | T21: New York | U21: - | V21: - | W21: St. John's | Y21: Canada | Z21: - | AA21: - | AB21: Job State, 24, stout fellow, M, (on his own bottom). Born free at New York. | AD21: 677 | AE21: - | AF21: Book One Part One | AG21: Amity's Production | AH21: Thomas Reid | AI21: Amity's Production bound for St. John's Thomas Reid, Master
A22: Mary | B22: State | C22: - | D22: - | E22: - | F22: - | G22: Male | H22: 21 | I22: 1762 | J22: Half Indian | K22: Mixed Race | L22: Mulatto | M22: - | N22: - | O22: Long Island | R22: =IFERROR(INDEX(Sheet2!$C:$C, MATCH(P22&Q22, Sheet2!$E:$E, 0)) & ", " & INDEX(Sheet2!$D:$D, MATCH(P22&Q22, Sheet2!$E:$E, 0)), "-") -> - | S22: - | T22: - | U22: - | V22: - | W22: St. John's | Y22: Canada | Z22: - | AA22: - | AB22: Mary State, 21, half Indian, (on her own bottom). Born free on Long Island. | AD22: 676 | AE22: - | AF22: Book One Part One | AG22: Amity's Production | AH22: Thomas Reid | AI22: Amity's Production bound for St. John's Thomas Reid, Master
A23: George | B23: State | C23: - | D23: - | E23: - | F23: - | G23: Male | H23: 25 | I23: 1758 | J23: Black | K23: African American | L23: Black | M23: - | N23: - | O23: New York | R23: =IFERROR(INDEX(Sheet2!$C:$C, MATCH(P23&Q23, Sheet2!$E:$E, 0)) & ", " & INDEX(Sheet2!$D:$D, MATCH(P23&Q23, Sheet2!$E:$E, 0)), "-") -> - | S23: - | T23: New York | U23: - | V23: - | W23: St. John's | Y23: Canada | Z23: - | AA23: - | AB23: George State, 25, stout fellow, M, (on his own bottom). Born free at New York. | AD23: 675 | AE23: - | AF23: Book One Part One | AG23: Amity's Production | AH23: Thomas Reid | AI23: Amity's Production bound for St. John's Thomas Reid, Master
A24: William | B24: Stepney | C24: - | D24: - | E24: - | F24: - | G24: Male | H24: 24 | I24: 1759 | J24: Black | K24: African American | L24: Black | M24: - | N24: - | O24: - | R24: =IFERROR(INDEX(Sheet2!$C:$C, MATCH(P24&Q24, Sheet2!$E:$E, 0)) & ", " & INDEX(Sheet2!$D:$D, MATCH(P24&Q24, Sheet2!$E:$E, 0)), "-") -> - | S24: - | T24: - | U24: - | V24: - | W24: St. John's | Y24: Canada | Z24: - | AA24: - | AB24: William Stepney, 24, stout fellow, B, (on his own bottom). Born free at St. Augustine. | AD24: 674 | AE24: - | AF24: Book One Part One | AG24: Amity's Production | AH24: Thomas Reid | AI24: Amity's Production bound for St. John's Thomas Reid, Master
A25: James | B25: Robertson | C25: - | D25: - | E25: - | F25: - | G25: Child Male | H25: 2½ | I25: - | J25: Black | K25: African American | L25: Black | M25: - | N25: - | O25: - | R25: =IFERROR(INDEX(Sheet2!$C:$C, MATCH(P25&Q25, Sheet2!$E:$E, 0)) & ", " & INDEX(Sheet2!$D:$D, MATCH(P25&Q25, Sheet2!$E:$E, 0)), "-") -> - | S25: New York | T25: - | U25: New York | V25: 8 Jul 1783 | W25: Port Roseway | Y25: Canada | Z25: Book of Negroes, British Headquarters Papers PRO 30/55/100; Loyalist evacuation shipping lists (1782–1784) | AA25: Loyalist evacuation lists | AB25: James Robertson, 2½, small boy, (Capt. Mowat). | AD25: 209 | AE25: 22 | AF25: Book One Part One | AG25: Ann | AH25: Joseph Clark | AI25: Ship Ann bound for Port Roseway Joseph Clark, Master
A26: Betsey | B26: Robertson | C26: - | D26: - | E26: Barbara | F26: Ogden | G26: Female | H26: 46 | I26: 1737 | J26: Black | K26: African American | L26: Black | M26: Portsmouth | N26: - | O26: Virginia | R26: =IFERROR(INDEX(Sheet2!$C:$C, MATCH(P26&Q26, Sheet2!$E:$E, 0)) & ", " & INDEX(Sheet2!$D:$D, MATCH(P26&Q26, Sheet2!$E:$E, 0)), "-") -> - | S26: New York | T26: Virginia | U26: New York | V26: Fall 1783 | W26: Port Roseway | Y26: Canada | Z26: Book of Negroes, British Headquarters Papers PRO 30/55/100; Loyalist evacuation shipping lists (1782–1784) | AA26: Loyalist evacuation lists | AB26: Betsey Robertson, 46, thin wench, (Capt. Mowat). Formerly slave to Captain Paul Layon, Portsmouth, Virginia; left him with her husband. | AD26: 208 | AE26: 22 | AF26: Book One Part One | AG26: Ann | AH26: Joseph Clark | AI26: Ship Ann bound for Port Roseway Joseph Clark, Master
A27: James | B27: Robertson | C27: - | D27: - | E27: - | F27: - | G27: Male | H27: 49 | I27: 1734 | J27: Black | K27: African American | L27: Black | M27: Portsmouth | N27: - | O27: Virginia | R27: =IFERROR(INDEX(Sheet2!$C:$C, MATCH(P27&Q27, Sheet2!$E:$E, 0)) & ", " & INDEX(Sheet2!$D:$D, MATCH(P27&Q27, Sheet2!$E:$E, 0)), "-") -> - | S27: New York | T27: Virginia | U27: New York | V27: 8 Jul 1783 | W27: Port Roseway | Y27: Canada | Z27: Book of Negroes, British Headquarters Papers PRO 30/55/100; Loyalist evacuation shipping lists (1782–1784) | AA27: Loyalist evacuation lists | AB27: James Robertson, 49, thin, pilot by order, (Capt. Mowat). Formerly slave to Captain Paul Layon, Portsmouth, Virginia; left him 4 years ago, employed as a pilot. | AD27: 207 | AE27: 22 | AF27: Book One Part One | AG27: Ann | AH27: Joseph Clark | AI27: Ship Ann bound for Port Roseway Joseph Clark, Master
A28: William | B28: - | C28: - | D28: - | E28: - | F28: - | G28: Child Male | H28: 14 | I28: 1769 | J28: Black | K28: African American | L28: Black | M28: Hugh Dunn | N28: New York | O28: Garrison | R28: =IFERROR(INDEX(Sheet2!$C:$C, MATCH(P28&Q28, Sheet2!$E:$E, 0)) & ", " & INDEX(Sheet2!$D:$D, MATCH(P28&Q28, Sheet2!$E:$E, 0)), "-") -> - | S28: New York | T28: New York | U28: New York | V28: Fall 1783 | W28: Port Roseway | Y28: Canada | Z28: Book of Negroes, British Headquarters Papers PRO 30/55/100; Loyalist evacuation shipping lists (1782–1784) | AA28: Loyalist evacuation lists | AB28: William, 14, fine boy. (John Anderson of Port Roseway, claimant.) John Anderson purchased from Hugh Dunn, New York; born nigh Stoney Point. Formerly the property of Edison, taken with a guard of the enemy by a party from the Garrison, 1779. | AD28: 239 | AE28: 22 | AF28: Book One Part One | AG28: Ann | AH28: Joseph Clark | AI28: Ship Ann bound for Port Roseway Joseph Clark, Master
A29: Joe | B29: Gold | C29: - | D29: - | E29: - | F29: - | G29: Male | H29: 30 | I29: 1753 | J29: Black | K29: African American | L29: Black | M29: Charlestown | N29: - | O29: South Carolina | R29: =IFERROR(INDEX(Sheet2!$C:$C, MATCH(P29&Q29, Sheet2!$E:$E, 0)) & ", " & INDEX(Sheet2!$D:$D, MATCH(P29&Q29, Sheet2!$E:$E, 0)), "-") -> - | S29: New York | T29: South Carolina | U29: New York | V29: Fall 1783 | W29: Port Roseway | Y29: Canada | Z29: Book of Negroes, British Headquarters Papers PRO 30/55/100; Loyalist evacuation shipping lists (1782–1784) | AA29: Loyalist evacuation lists | AB29: Joe Gold, 30, stout black, (Robert Turnbull). Formerly slave to Daniel Descan , about 14 miles from Charlestown, South Carolina; left him 4 years ago. | AD29: 240 | AE29: 23 | AF29: Book One Part One | AG29: Ann | AH29: Joseph Clark | AI29: Ship Ann bound for Port Roseway Joseph Clark, Master
A30: Effie | B30: Warner | C30: - | D30: - | E30: - | F30: - | G30: Child Female | H30: 33 | I30: 1750 | J30: Black | K30: African American | L30: Black | M30: - | N30: - | O30: Virginia | R30: =IFERROR(INDEX(Sheet2!$C:$C, MATCH(P30&Q30, Sheet2!$E:$E, 0)) & ", " & INDEX(Sheet2!$D:$D, MATCH(P30&Q30, Sheet2!$E:$E, 0)), "-") -> - | S30: Princess Ann | T30: Virginia | U30: - | V30: - | W30: Port Roseway | Y30: Canada | Z30: - | AA30: - | AB30: Effie Warner, 33, stout wench & boy 2 yrs, old, (William Hill). Formerly slave to John Matthews, Princess Ann, Virginia; left him 5 years ago. GBC. | AD30: 236 | AE30: - | AF30: Book One Part One | AG30: Ann | AH30: Joseph Clark | AI30: Ship Ann bound for Port Roseway Joseph Clark, Master
A31: Sukey | B31: her daughter | C31: - | D31: - | E31: Betsey | F31: his wife | G31: Child Female | H31: 12 | I31: 1771 | J31: Mulatto | K31: Mixed Race | L31: Mulatto | M31: Savannah | N31: - | O31: Georgia | R31: =IFERROR(INDEX(Sheet2!$C:$C, MATCH(P31&Q31, Sheet2!$E:$E, 0)) & ", " & INDEX(Sheet2!$D:$D, MATCH(P31&Q31, Sheet2!$E:$E, 0)), "-") -> - | S31: New York | T31: Georgia | U31: New York | V31: Fall 1783 | W31: Port Roseway | Y31: Canada | Z31: Book of Negroes, British Headquarters Papers PRO 30/55/100; Loyalist evacuation shipping lists (1782–1784) | AA31: Loyalist evacuation lists | AB31: Sukey her daughter, 12, thin mulatto girl, (Robert Turnbull). Formerly slave to Mrs. Harriet Crook, Savannah, Georgia; left that place 5 years ago. | AD31: 242 | AE31: 23 | AF31: Book One Part One | AG31: Ann | AH31: Joseph Clark | AI31: Ship Ann bound for Port Roseway Joseph Clark, Master
A32: James | B32: Jackson 50 | C32: - | D32: - | E32: - | F32: - | G32: Male | H32: 50 | I32: 1733 | J32: Black | K32: African American | L32: Black | M32: Norfolk | N32: - | O32: Virginia | R32: =IFERROR(INDEX(Sheet2!$C:$C, MATCH(P32&Q32, Sheet2!$E:$E, 0)) & ", " & INDEX(Sheet2!$D:$D, MATCH(P32&Q32, Sheet2!$E:$E, 0)), "-") -> - | S32: New York | T32: Virginia | U32: New York | V32: 8 Jul 1783 | W32: Port Roseway | Y32: Canada | Z32: Book of Negroes, British Headquarters Papers PRO 30/55/100; Loyalist evacuation shipping lists (1782–1784) | AA32: Loyalist evacuation lists | AB32: James Jackson 50, thin, goes as pilot (Capt. Mowat). Formerly slave to late Robert Tucker, Norfolk, Virginia; left him with Lord Dunmore when he left that country & was employed as a pilot. | AD32: 210 | AE32: 22 | AF32: Book One Part One | AG32: Ann | AH32: Joseph Clark | AI32: Ship Ann bound for Port Roseway Joseph Clark, Master
A33: Elizabeth | B33: Mitchell | C33: - | D33: - | E33: - | F33: - | G33: Child Female | H33: 13 | I33: 1770 | J33: Black | K33: African American | L33: Black | M33: Charlestown | N33: - | O33: South Carolina | R33: =IFERROR(INDEX(Sheet2!$C:$C, MATCH(P33&Q33, Sheet2!$E:$E, 0)) & ", " & INDEX(Sheet2!$D:$D, MATCH(P33&Q33, Sheet2!$E:$E, 0)), "-") -> - | S33: New York | T33: South Carolina | U33: New York | V33: Fall 1783 | W33: St. John's | Y33: Canada | Z33: Book of Negroes, British Headquarters Papers PRO 30/55/100; Loyalist evacuation shipping lists (1782–1784) | AA33: Loyalist evacuation lists | AB33: Elizabeth Mitchell, 13, stout girl, (Lt. Clows, Guides & Pioneers). Says she was born free near Charlestown, South Carolina; joined the Army in 1780. | AD33: 1946 | AE33: 61 | AF33: Book One Part Two | AG33: Ann | AH33: Clark | AI33: Ann bound for St. John's Clark
A34: Dick | B34: Vincent | C34: - | D34: - | E34: - | F34: - | G34: Child Male | H34: 10 | I34: 1773 | J34: Black | K34: African American | L34: Black | M34: - | N34: - | O34: East Chester | R34: =IFERROR(INDEX(Sheet2!$C:$C, MATCH(P34&Q34, Sheet2!$E:$E, 0)) & ", " & INDEX(Sheet2!$D:$D, MATCH(P34&Q34, Sheet2!$E:$E, 0)), "-") -> - | S34: New York | T34: - | U34: New York | V34: Fall 1783 | W34: St. John's | Y34: Canada | Z34: Book of Negroes, British Headquarters Papers PRO 30/55/100; Loyalist evacuation shipping lists (1782–1784) | AA34: Loyalist evacuation lists | AB34: Dick Vincent, 10, stout boy, (Ens. Vincent). Formerly slave to Charles Vincent, East Chester, grandfather to the Ensign who has delivered the boy to the said Ensign. | AD34: 1947 | AE34: 22 | AF34: Book One Part Two | AG34: Ann | AH34: Clark | AI34: Ann bound for St. John's Clark
A35: child of | B35: Abigail | G35: c | H35: 4 months | I35: - | M35: - | N35: - | O35: - | R35: =IFERROR(INDEX(Sheet2!$C:$C, MATCH(P35&Q35, Sheet2!$E:$E, 0)) & ", " & INDEX(Sheet2!$D:$D, MATCH(P35&Q35, Sheet2!$E:$E, 0)), "-") -> - | S35: New York | U35: New York | V35: Fall 1783 | W35: Port Roseway | Y35: Canada | Z35: Book of Negroes, British Headquarters Papers PRO 30/55/100; Loyalist evacuation shipping lists (1782–1784) | AA35: Loyalist evacuation lists | AD35: 250 | AE35: 22 | AG35: Ann | AH35: Joseph Clark
A36: Betsey his | B36: wife | G36: Female | H36: 33 | I36: 1750 | M36: - | N36: - | O36: - | R36: =IFERROR(INDEX(Sheet2!$C:$C, MATCH(P36&Q36, Sheet2!$E:$E, 0)) & ", " & INDEX(Sheet2!$D:$D, MATCH(P36&Q36, Sheet2!$E:$E, 0)), "-") -> - | S36: New York | U36: New York | V36: Fall 1783 | W36: Port Roseway | Y36: Canada | Z36: Book of Negroes, British Headquarters Papers PRO 30/55/100; Loyalist evacuation shipping lists (1782–1784) | AA36: Loyalist evacuation lists | AD36: 263 | AE36: 23 | AG36: Ann | AH36: Joseph Clark
A37: Sukey her | B37: daughter | G37: Child Female | H37: 12 | I37: 1771 | M37: - | N37: - | O37: - | R37: =IFERROR(INDEX(Sheet2!$C:$C, MATCH(P37&Q37, Sheet2!$E:$E, 0)) & ", " & INDEX(Sheet2!$D:$D, MATCH(P37&Q37, Sheet2!$E:$E, 0)), "-") -> - | S37: New York | U37: New York | V37: Fall 1783 | W37: Port Roseway | Y37: Canada | Z37: Book of Negroes, British Headquarters Papers PRO 30/55/100; Loyalist evacuation shipping lists (1782–1784) | AA37: Loyalist evacuation lists | AD37: 264 | AE37: 23 | AG37: Ann | AH37: Joseph Clark
A38: Betsey | B38: his wife | C38: - | D38: - | E38: - | F38: - | G38: Female | H38: 33 | I38: 1750 | J38: Mulatto | K38: Mixed Race | L38: Mulatto | M38: Savannah | N38: - | O38: Georgia | R38: =IFERROR(INDEX(Sheet2!$C:$C, MATCH(P38&Q38, Sheet2!$E:$E, 0)) & ", " & INDEX(Sheet2!$D:$D, MATCH(P38&Q38, Sheet2!$E:$E, 0)), "-") -> - | S38: New York | T38: Georgia | U38: New York | V38: Fall 1783 | W38: Port Roseway | Y38: Canada | Z38: Book of Negroes, British Headquarters Papers PRO 30/55/100; Loyalist evacuation shipping lists (1782–1784) | AA38: Loyalist evacuation lists | AB38: Betsey his wife, 33, stout mulatto wench, (Robert Turnbull). Formerly slave to Mrs. Harriet Crook, Savannah, Georgia; left that place 5 years ago. | AD38: 241 | AE38: 22 | AF38: Book One Part One | AG38: Ann | AH38: Joseph Clark | AI38: Ship Ann bound for Port Roseway Joseph Clark, Master
A39: Judith | B39: Jackson | C39: - | D39: - | E39: Betsey | F39: Robertson | G39: Female | H39: 24 | I39: 1759 | J39: Mulatto | K39: Mixed Race | L39: Mulatto | M39: - | N39: - | O39: - | R39: =IFERROR(INDEX(Sheet2!$C:$C, MATCH(P39&Q39, Sheet2!$E:$E, 0)) & ", " & INDEX(Sheet2!$D:$D, MATCH(P39&Q39, Sheet2!$E:$E, 0)), "-") -> - | S39: New York | T39: - | U39: New York | V39: Fall 1783 | W39: Port Roseway | Y39: Canada | Z39: Book of Negroes, British Headquarters Papers PRO 30/55/100; Loyalist evacuation shipping lists (1782–1784) | AA39: Loyalist evacuation lists | AB39: Judith Jackson, 24, thin wench, mulatto, (Capt. Mowat). Says she served her time to John Bell at Cape Fear and left that with the army of Sir H. Clinton in 1776. | AD39: 211 | AE39: 22 | AF39: Book One Part One | AG39: Ann | AH39: Joseph Clark | AI39: Ship Ann bound for Port Roseway Joseph Clark, Master
A40: Harry | B40: Jackson | C40: - | D40: - | E40: - | F40: - | G40: Child Male | H40: 8 | I40: 1775 | J40: Black | K40: African American | L40: Black | M40: - | N40: - | O40: - | R40: =IFERROR(INDEX(Sheet2!$C:$C, MATCH(P40&Q40, Sheet2!$E:$E, 0)) & ", " & INDEX(Sheet2!$D:$D, MATCH(P40&Q40, Sheet2!$E:$E, 0)), "-") -> - | S40: New York | T40: - | U40: New York | V40: Fall 1783 | W40: Port Roseway | Y40: Canada | Z40: Book of Negroes, British Headquarters Papers PRO 30/55/100; Loyalist evacuation shipping lists (1782–1784) | AA40: Loyalist evacuation lists | AB40: Harry Jackson, 8, good L boy, (Capt. Mowat). | AD40: 212 | AE40: 22 | AF40: Book One Part One | AG40: Ann | AH40: Joseph Clark | AI40: Ship Ann bound for Port Roseway Joseph Clark, Master
A41: Charles | B41: Fox | C41: - | D41: - | E41: - | F41: - | G41: Male | H41: 33 | I41: 1750 | J41: Black | K41: African American | L41: Black | M41: Gloster | N41: - | O41: Virginia | R41: =IFERROR(INDEX(Sheet2!$C:$C, MATCH(P41&Q41, Sheet2!$E:$E, 0)) & ", " & INDEX(Sheet2!$D:$D, MATCH(P41&Q41, Sheet2!$E:$E, 0)), "-") -> - | S41: New York | T41: Virginia | U41: New York | V41: Fall 1783 | W41: Port Roseway | Y41: Canada | Z41: Book of Negroes, British Headquarters Papers PRO 30/55/100; Loyalist evacuation shipping lists (1782–1784) | AA41: Loyalist evacuation lists | AB41: Charles Fox, 33, stout fellow, (John Anderson). Formerly slave to John Fox, Gloster, Virginia; left him about five years ago by proclamation. GBC. | AD41: 213 | AE41: 22 | AF41: Book One Part One | AG41: Ann | AH41: Joseph Clark | AI41: Ship Ann bound for Port Roseway Joseph Clark, Master
A42: Peter | B42: Warner | C42: - | D42: - | E42: - | F42: - | G42: Male | H42: 30 | I42: 1753 | J42: Black | K42: African American | L42: Black | M42: Monmouth | N42: - | O42: New Jersey | R42: =IFERROR(INDEX(Sheet2!$C:$C, MATCH(P42&Q42, Sheet2!$E:$E, 0)) & ", " & INDEX(Sheet2!$D:$D, MATCH(P42&Q42, Sheet2!$E:$E, 0)), "-") -> - | S42: New York | T42: New Jersey | U42: New York | V42: Fall 1783 | W42: Port Roseway | Y42: Canada | Z42: Book of Negroes, British Headquarters Papers PRO 30/55/100; Loyalist evacuation shipping lists (1782–1784) | AA42: Loyalist evacuation lists | AB42: Peter Warner, 30, stout, cut above his left eye, (William Hill). Formerly slave to Michael Mount, Monmouth, New Jersey; left him 5 years ago. GBC. | AD42: 235 | AE42: 22 | AF42: Book One Part One | AG42: Ann | AH42: Joseph Clark | AI42: Ship Ann bound for Port Roseway Joseph Clark, Master
A43: Casar | B43: Nicholls | C43: - | D43: - | E43: - | F43: - | G43: Male | H43: 22 | I43: 1761 | J43: Black | K43: African American | L43: Black | M43: - | N43: - | O43: - | R43: =IFERROR(INDEX(Sheet2!$C:$C, MATCH(P43&Q43, Sheet2!$E:$E, 0)) & ", " & INDEX(Sheet2!$D:$D, MATCH(P43&Q43, Sheet2!$E:$E, 0)), "-") -> - | S43: - | T43: - | U43: - | V43: - | W43: Port Roseway | Y43: Canada | Z43: - | AA43: - | AB43: Casar Nicholls, 22, stout black man, (William Hill). Formerly slave to Dr. Van Wyck at Fishkills; left him 3½ years ago. | AD43: 234 | AE43: - | AF43: Book One Part One | AG43: Ann | AH43: Joseph Clark | AI43: Ship Ann bound for Port Roseway Joseph Clark, Master
A44: Judah | B44: Pell | C44: - | D44: - | E44: - | F44: - | G44: Child Female | H44: 25 | I44: 1758 | J44: Black | K44: African American | L44: Black | M44: Norfolk | N44: - | O44: Virginia | R44: =IFERROR(INDEX(Sheet2!$C:$C, MATCH(P44&Q44, Sheet2!$E:$E, 0)) & ", " & INDEX(Sheet2!$D:$D, MATCH(P44&Q44, Sheet2!$E:$E, 0)), "-") -> - | S44: New York | T44: Virginia | U44: New York | V44: Fall 1783 | W44: Port Roseway | Y44: Canada | Z44: Book of Negroes, British Headquarters Papers PRO 30/55/100; Loyalist evacuation shipping lists (1782–1784) | AA44: Loyalist evacuation lists | AB44: Judah Pell, 25, S.B. Wench, child 5 yrs, old, (William Hill). Formerly slave to Dr. Ramsey, Norfolk, Virginia; left him about five years ago. | AD44: 233 | AE44: 22 | AF44: Book One Part One | AG44: Ann | AH44: Joseph Clark | AI44: Ship Ann bound for Port Roseway Joseph Clark, Master
A45: John | B45: Pell | C45: - | D45: - | E45: - | F45: - | G45: Child Male | H45: 14 | I45: 1769 | J45: Mulatto | K45: Mixed Race | L45: Mulatto | M45: - | N45: - | O45: - | R45: =IFERROR(INDEX(Sheet2!$C:$C, MATCH(P45&Q45, Sheet2!$E:$E, 0)) & ", " & INDEX(Sheet2!$D:$D, MATCH(P45&Q45, Sheet2!$E:$E, 0)), "-") -> - | S45: New York | T45: - | U45: New York | V45: Fall 1783 | W45: Port Roseway | Y45: Canada | Z45: Book of Negroes, British Headquarters Papers PRO 30/55/100; Loyalist evacuation shipping lists (1782–1784) | AA45: Loyalist evacuation lists | AB45: John Pell, 14, stout mulatto boy, (William Hill). Son to the above mentioned person. | AD45: 232 | AE45: 22 | AF45: Book One Part One | AG45: Ann | AH45: Joseph Clark | AI45: Ship Ann bound for Port Roseway Joseph Clark, Master
A46: John | B46: Pell | C46: - | D46: - | E46: - | F46: - | G46: Male | H46: 28 | I46: 1755 | J46: Black | K46: African American | L46: Black | M46: - | N46: - | O46: Charlestown | R46: =IFERROR(INDEX(Sheet2!$C:$C, MATCH(P46&Q46, Sheet2!$E:$E, 0)) & ", " & INDEX(Sheet2!$D:$D, MATCH(P46&Q46, Sheet2!$E:$E, 0)), "-") -> - | S46: New York | T46: - | U46: New York | V46: Fall 1783 | W46: Port Roseway | Y46: Canada | Z46: Book of Negroes, British Headquarters Papers PRO 30/55/100; Loyalist evacuation shipping lists (1782–1784) | AA46: Loyalist evacuation lists | AB46: John Pell, 28, stout man, pock marked, (William Hill). Free as appears by a Certificate of General Birch to whom he was given by Sir Henry Clinton; says he left Charlestown about 5 years ago. | AD46: 231 | AE46: 22 | AF46: Book One Part One | AG46: Ann | AH46: Joseph Clark | AI46: Ship Ann bound for Port Roseway Joseph Clark, Master
A47: Abigail | B47: - | C47: - | D47: - | E47: - | F47: - | G47: Child Male | H47: 35 | I47: 1748 | J47: Black | K47: African American | L47: Black | M47: Brunswick | N47: - | O47: New Jersey | R47: =IFERROR(INDEX(Sheet2!$C:$C, MATCH(P47&Q47, Sheet2!$E:$E, 0)) & ", " & INDEX(Sheet2!$D:$D, MATCH(P47&Q47, Sheet2!$E:$E, 0)), "-") -> - | S47: New York | T47: New Jersey | U47: New York | V47: Fall 1783 | W47: Port Roseway | Y47: Canada | Z47: Book of Negroes, British Headquarters Papers PRO 30/55/100; Loyalist evacuation shipping lists (1782–1784) | AA47: Loyalist evacuation lists | AB47: Abigail, 35, stout child 4 mo. (Thomas Statia). Formerly slave to White at Brunswick, New Jersey; left him five years ago. | AD47: 230 | AE47: 22 | AF47: Book One Part One | AG47: Ann | AH47: Joseph Clark | AI47: Ship Ann bound for Port Roseway Joseph Clark, Master
A48: Judah | B48: Few | C48: - | D48: - | E48: - | F48: - | G48: Child Female | H48: 35 | I48: 1748 | J48: Black | K48: African American | L48: Black | M48: Newtown | N48: - | O48: Long Island | R48: =IFERROR(INDEX(Sheet2!$C:$C, MATCH(P48&Q48, Sheet2!$E:$E, 0)) & ", " & INDEX(Sheet2!$D:$D, MATCH(P48&Q48, Sheet2!$E:$E, 0)), "-") -> - | S48: New York | T48: - | U48: New York | V48: Fall 1783 | W48: Port Roseway | Y48: Canada | Z48: Book of Negroes, British Headquarters Papers PRO 30/55/100; Loyalist evacuation shipping lists (1782–1784) | AA48: Loyalist evacuation lists | AB48: Judah Few, 35, stout M wench, child 5 years old. (Robert McCulloch). Free born, James Way's, English Kills, Newtown, Long Island. | AD48: 229 | AE48: 22 | AF48: Book One Part One | AG48: Ann | AH48: Joseph Clark | AI48: Ship Ann bound for Port Roseway Joseph Clark, Master
A49: Prince | B49: Few | C49: - | D49: - | E49: - | F49: - | G49: Male | H49: 26 | I49: 1757 | J49: Mulatto | K49: Mixed Race | L49: Mulatto | M49: - | N49: - | O49: Connecticut | R49: =IFERROR(INDEX(Sheet2!$C:$C, MATCH(P49&Q49, Sheet2!$E:$E, 0)) & ", " & INDEX(Sheet2!$D:$D, MATCH(P49&Q49, Sheet2!$E:$E, 0)), "-") -> - | S49: New York | T49: - | U49: New York | V49: Fall 1783 | W49: Port Roseway | Y49: Canada | Z49: Book of Negroes, British Headquarters Papers PRO 30/55/100; Loyalist evacuation shipping lists (1782–1784) | AA49: Loyalist evacuation lists | AB49: Prince Few, 26, thin mulatto, (Robert McCulloch). Free born, Pearson town, Connecticut. | AD49: 228 | AE49: 22 | AF49: Book One Part One | AG49: Ann | AH49: Joseph Clark | AI49: Ship Ann bound for Port Roseway Joseph Clark, Master
... A74: Dinah | B74: his wife | C74: - | D74: - | E74: Dinah | F74: Edmonds | G74: Child Female | H74: 23 | I74: 1760 | J74: Black | K74: Mixed Race | L74: Black | M74: - | N74: - | O74: - | R74: =IFERROR(INDEX(Sheet2!$C:$C, MATCH(P74&Q74, Sheet2!$E:$E, 0)) & ", " & INDEX(Sheet2!$D:$D, MATCH(P74&Q74, Sheet2!$E:$E, 0)), "-") -> - | S74: New York | T74: - | U74: New York | V74: 1783 | W74: Port Roseway | Y74: Canada | Z74: Book of Negroes, British Headquarters Papers PRO 30/55/100; Loyalist evacuation shipping lists (1782–1784) | AA74: Book of Negroes | AB74: Dinah his wife, 23, lusty, squat wench, B, small child (Nicholas Browne). Born free, her mother an Indian; served her time with Edmund Palmer who lived & was hanged at Fishkill for being Tory. | AD74: 432 | AE74: 27 | AF74: Book One Part One | AG74: Ann & Elizabeth | AH74: Ben Fowler | AI74: Ship Ann & Elizabeth bound for Port Roseway Ben Fowler, Master
A75: Nancy his | B75: wife | G75: Female | H75: 40 | I75: 1743 | M75: - | N75: - | O75: - | R75: =IFERROR(INDEX(Sheet2!$C:$C, MATCH(P75&Q75, Sheet2!$E:$E, 0)) & ", " & INDEX(Sheet2!$D:$D, MATCH(P75&Q75, Sheet2!$E:$E, 0)), "-") -> - | S75: New York | U75: New York | V75: 1783 | W75: Port Roseway | Y75: Canada | Z75: Book of Negroes, British Headquarters Papers PRO 30/55/100; Loyalist evacuation shipping lists (1782–1784) | AA75: Book of Negroes | AD75: 478 | AE75: 27 | AG75: Ann & Elizabeth | AH75: Ben Fowler
A76: Dinah Browne his | B76: wife | G76: Female | H76: 23 | I76: 1760 | M76: - | N76: - | O76: - | R76: =IFERROR(INDEX(Sheet2!$C:$C, MATCH(P76&Q76, Sheet2!$E:$E, 0)) & ", " & INDEX(Sheet2!$D:$D, MATCH(P76&Q76, Sheet2!$E:$E, 0)), "-") -> - | S76: New York | U76: New York | V76: 1783 | W76: Port Roseway | Y76: Canada | Z76: Book of Negroes, British Headquarters Papers PRO 30/55/100; Loyalist evacuation shipping lists (1782–1784) | AA76: Book of Negroes | AD76: 475 | AE76: 27 | AG76: Ann & Elizabeth | AH76: Ben Fowler
A77: child of | B77: Hannah | G77: c | I77: - | M77: - | N77: - | O77: - | R77: =IFERROR(INDEX(Sheet2!$C:$C, MATCH(P77&Q77, Sheet2!$E:$E, 0)) & ", " & INDEX(Sheet2!$D:$D, MATCH(P77&Q77, Sheet2!$E:$E, 0)), "-") -> - | S77: New York | U77: New York | V77: 1783 | W77: Port Roseway | Y77: Canada | Z77: Book of Negroes, British Headquarters Papers PRO 30/55/100; Loyalist evacuation shipping lists (1782–1784) | AA77: Book of Negroes | AD77: 473 | AE77: 27 | AG77: Ann & Elizabeth | AH77: Ben Fowler
A78: child of | B78: Hannah | G78: c | I78: - | M78: - | N78: - | O78: - | R78: =IFERROR(INDEX(Sheet2!$C:$C, MATCH(P78&Q78, Sheet2!$E:$E, 0)) & ", " & INDEX(Sheet2!$D:$D, MATCH(P78&Q78, Sheet2!$E:$E, 0)), "-") -> - | S78: New York | U78: New York | V78: 1783 | W78: Port Roseway | Y78: Canada | Z78: Book of Negroes, British Headquarters Papers PRO 30/55/100; Loyalist evacuation shipping lists (1782–1784) | AA78: Book of Negroes | AD78: 472 | AE78: 27 | AG78: Ann & Elizabeth | AH78: Ben Fowler
A79: Hannah his | B79: wife | G79: Female | H79: 23 | I79: 1760 | M79: - | N79: - | O79: - | R79: =IFERROR(INDEX(Sheet2!$C:$C, MATCH(P79&Q79, Sheet2!$E:$E, 0)) & ", " & INDEX(Sheet2!$D:$D, MATCH(P79&Q79, Sheet2!$E:$E, 0)), "-") -> - | S79: New York | U79: New York | V79: 1783 | W79: Port Roseway | Y79: Canada | Z79: Book of Negroes, British Headquarters Papers PRO 30/55/100; Loyalist evacuation shipping lists (1782–1784) | AA79: Book of Negroes | AD79: 471 | AE79: 27 | AG79: Ann & Elizabeth | AH79: Ben Fowler
A80: Tom | B80: - | C80: - | D80: - | E80: - | F80: - | G80: Male | H80: 40 | I80: 1743 | J80: Black | K80: African American | L80: Black | M80: Charlestown | N80: - | O80: South Carolina | R80: =IFERROR(INDEX(Sheet2!$C:$C, MATCH(P80&Q80, Sheet2!$E:$E, 0)) & ", " & INDEX(Sheet2!$D:$D, MATCH(P80&Q80, Sheet2!$E:$E, 0)), "-") -> - | S80: New York | T80: South Carolina | U80: New York | V80: 1783 | W80: Port Roseway | Y80: Canada | Z80: Book of Negroes, British Headquarters Papers PRO 30/55/100; Loyalist evacuation shipping lists (1782–1784) | AA80: Book of Negroes | AB80: Tom, 40, sickly man, (Thomas Hartley). Formerly slave to Henry Smith, Charlestown, South Carolina, who died soon after it was taken by the British; left no heirs. | AD80: 433 | AE80: 27 | AF80: Book One Part One | AG80: Ann & Elizabeth | AH80: Ben Fowler | AI80: Ship Ann & Elizabeth bound for Port Roseway Ben Fowler, Master
A81: George | B81: Barnes | C81: - | D81: - | E81: - | F81: - | G81: Male | H81: 47 | I81: 1736 | J81: Black | K81: African American | L81: Black | M81: Newport | N81: - | O81: Rhode Island | R81: =IFERROR(INDEX(Sheet2!$C:$C, MATCH(P81&Q81, Sheet2!$E:$E, 0)) & ", " & INDEX(Sheet2!$D:$D, MATCH(P81&Q81, Sheet2!$E:$E, 0)), "-") -> - | S81: New York | T81: - | U81: New York | V81: 1783 | W81: - | Y81: Canada | Z81: Book of Negroes, British Headquarters Papers PRO 30/55/100; Loyalist evacuation shipping lists (1782–1784) | AA81: Book of Negroes | AB81: George Barnes, 47, feeble fellow, goes as Cook to the Ship. Says he is a free man; produces a Certificate dated 1770 from John Davis of Newport, Rhode Island, Justice of the Peace. | AD81: 1798 | AE81: 58 | AF81: Book One Part Two | AG81: Ann & Elizabeth | AH81: - | AI81: Ann & Elizabeth bound for Spithead & Germany Ben Fowler
A82: Prince | B82: Fraction | C82: - | D82: - | E82: - | F82: - | G82: Male | H82: 25 | I82: 1758 | J82: Black | K82: African American | L82: Black | M82: Prince Fraction | N82: Port Roseway | O82: New York | R82: =IFERROR(INDEX(Sheet2!$C:$C, MATCH(P82&Q82, Sheet2!$E:$E, 0)) & ", " & INDEX(Sheet2!$D:$D, MATCH(P82&Q82, Sheet2!$E:$E, 0)), "-") -> - | S82: New York | T82: New York | U82: New York | V82: 1783 | W82: Port Roseway | Y82: Canada | Z82: Book of Negroes, British Headquarters Papers PRO 30/55/100; Loyalist evacuation shipping lists (1782–1784) | AA82: Book of Negroes | AB82: Prince Fraction, 25, stout blind left eye, Edward Trigler of Port Roseway, claimant (Edward Trigler). Property of Edward Trigler, purchased from James Stokes of New York. | AD82: 435 | AE82: 27 | AF82: Book One Part One | AG82: Ann & Elizabeth | AH82: Ben Fowler | AI82: Ship Ann & Elizabeth bound for Port Roseway Ben Fowler, Master
A83: Nancy | B83: his wife | C83: - | D83: - | E83: - | F83: - | G83: Female | H83: 40 | I83: 1743 | J83: Black | K83: African American | L83: Black | M83: - | N83: - | O83: - | R83: =IFERROR(INDEX(Sheet2!$C:$C, MATCH(P83&Q83, Sheet2!$E:$E, 0)) & ", " & INDEX(Sheet2!$D:$D, MATCH(P83&Q83, Sheet2!$E:$E, 0)), "-") -> - | S83: New York | T83: - | U83: New York | V83: 1783 | W83: Port Roseway | Y83: Canada | Z83: Book of Negroes, British Headquarters Papers PRO 30/55/100; Loyalist evacuation shipping lists (1782–1784) | AA83: Book of Negroes | AB83: Nancy his wife, 40, thin wench, (Thomas Hartley). Formerly slave to Widow Lott of Charlestown Elliot of Charlestown who she says gave her free before she died 11 years ago. | AD83: 434 | AE83: 27 | AF83: Book One Part One | AG83: Ann & Elizabeth | AH83: Ben Fowler | AI83: Ship Ann & Elizabeth bound for Port Roseway Ben Fowler, Master
A84: Peter | B84: Johnson | C84: John | D84: Voice | E84: - | F84: - | G84: Male | H84: 35 | I84: 1748 | J84: Black | K84: African American | L84: Black | M84: New Jersey | N84: - | O84: New York | R84: =IFERROR(INDEX(Sheet2!$C:$C, MATCH(P84&Q84, Sheet2!$E:$E, 0)) & ", " & INDEX(Sheet2!$D:$D, MATCH(P84&Q84, Sheet2!$E:$E, 0)), "-") -> - | S84: New York | T84: New Jersey | U84: New York | V84: 1783 | W84: Port Roseway | Y84: Canada | Z84: Book of Negroes, British Headquarters Papers PRO 30/55/100; Loyalist evacuation shipping lists (1782–1784) | AA84: Book of Negroes | AB84: Peter Johnson, 35, stout fellow, (Stephen Shakespeare). Says he got his freedom from Silvester Brinoly, Quaker, New Jersey; that he has lived in New York these 6 years past. GBC. | AD84: 416 | AE84: 27 | AF84: Book One Part One | AG84: Ann & Elizabeth | AH84: Ben Fowler | AI84: Ship Ann & Elizabeth bound for Port Roseway Ben Fowler, Master
A85: Judith | B85: Johnson | C85: - | D85: - | E85: - | F85: - | G85: Female | H85: 27 | I85: 1756 | J85: Black | K85: African American | L85: Black | M85: - | N85: - | O85: Shrewsbury | R85: =IFERROR(INDEX(Sheet2!$C:$C, MATCH(P85&Q85, Sheet2!$E:$E, 0)) & ", " & INDEX(Sheet2!$D:$D, MATCH(P85&Q85, Sheet2!$E:$E, 0)), "-") -> - | S85: New York | T85: - | U85: New York | V85: 1783 | W85: Port Roseway | Y85: Canada | Z85: Book of Negroes, British Headquarters Papers PRO 30/55/100; Loyalist evacuation shipping lists (1782–1784) | AA85: Book of Negroes | AB85: Judith Johnson, 27, ordinary wench, (Stephen Shakespeare). Formerly slave to Gerrit Langston, Shrewsbury; left him 3 years past. GBC. | AD85: 417 | AE85: 27 | AF85: Book One Part One | AG85: Ann & Elizabeth | AH85: Ben Fowler | AI85: Ship Ann & Elizabeth bound for Port Roseway Ben Fowler, Master
A86: Thomas | B86: Danvers | C86: - | D86: - | E86: - | F86: - | G86: Male | H86: 45 | I86: 1738 | J86: Black | K86: African American | L86: Black | M86: - | N86: - | O86: Savannah | R86: =IFERROR(INDEX(Sheet2!$C:$C, MATCH(P86&Q86, Sheet2!$E:$E, 0)) & ", " & INDEX(Sheet2!$D:$D, MATCH(P86&Q86, Sheet2!$E:$E, 0)), "-") -> - | S86: New York | T86: - | U86: New York | V86: 1783 | W86: Port Roseway | Y86: Canada | Z86: Book of Negroes, British Headquarters Papers PRO 30/55/100; Loyalist evacuation shipping lists (1782–1784) | AA86: Book of Negroes | AB86: Thomas Danvers, 45, ordinary fellow, (Archibald Clarke). Formerly slave to Thomas Brown, Savannah; left him 5 years past. | AD86: 418 | AE86: 27 | AF86: Book One Part One | AG86: Ann & Elizabeth | AH86: Ben Fowler | AI86: Ship Ann & Elizabeth bound for Port Roseway Ben Fowler, Master
A87: Rachel | B87: - | C87: - | D87: - | E87: - | F87: - | G87: Child Male | H87: 7 | I87: 1776 | J87: Black | K87: African American | L87: Black | M87: - | N87: - | O87: Rachel | R87: =IFERROR(INDEX(Sheet2!$C:$C, MATCH(P87&Q87, Sheet2!$E:$E, 0)) & ", " & INDEX(Sheet2!$D:$D, MATCH(P87&Q87, Sheet2!$E:$E, 0)), "-") -> - | S87: New York | T87: - | U87: New York | V87: 1783 | W87: - | Y87: Canada | Z87: Book of Negroes, British Headquarters Papers PRO 30/55/100; Loyalist evacuation shipping lists (1782–1784) | AA87: Book of Negroes | AB87: Rachel, 7, fine child. Daughter to George Barnes. | AD87: 1799 | AE87: 58 | AF87: Book One Part Two | AG87: Ann & Elizabeth | AH87: - | AI87: Ann & Elizabeth bound for Spithead & Germany Ben Fowler
A88: Harry | B88: Spencell | C88: - | D88: - | E88: - | F88: - | G88: Male | H88: 38 | I88: 1745 | J88: Black | K88: African American | L88: Black | M88: - | N88: - | O88: New York Island | R88: =IFERROR(INDEX(Sheet2!$C:$C, MATCH(P88&Q88, Sheet2!$E:$E, 0)) & ", " & INDEX(Sheet2!$D:$D, MATCH(P88&Q88, Sheet2!$E:$E, 0)), "-") -> - | S88: New York | T88: New York | U88: New York | V88: 1783 | W88: Port Roseway | Y88: Canada | Z88: Book of Negroes, British Headquarters Papers PRO 30/55/100; Loyalist evacuation shipping lists (1782–1784) | AA88: Book of Negroes | AB88: Harry Spencell, 38, slender fellow, (Stephen Hairran). Formerly slave to B. Benson left him on the Landing of the British troops on New York Island. | AD88: 420 | AE88: 27 | AF88: Book One Part One | AG88: Ann & Elizabeth | AH88: Ben Fowler | AI88: Ship Ann & Elizabeth bound for Port Roseway Ben Fowler, Master
A89: Henry | B89: Maxfield | C89: - | D89: - | E89: - | F89: - | G89: Male | H89: 33 | I89: 1750 | J89: Black | K89: African American | L89: Black | M89: - | N89: - | O89: - | R89: =IFERROR(INDEX(Sheet2!$C:$C, MATCH(P89&Q89, Sheet2!$E:$E, 0)) & ", " & INDEX(Sheet2!$D:$D, MATCH(P89&Q89, Sheet2!$E:$E, 0)), "-") -> - | S89: New York | T89: - | U89: New York | V89: 1783 | W89: Port Roseway | Y89: Canada | Z89: Book of Negroes, British Headquarters Papers PRO 30/55/100; Loyalist evacuation shipping lists (1782–1784) | AA89: Book of Negroes | AB89: Henry Maxfield, 33, stout fellow, (Alexander Watson). Free born in Mr. Philips's house of Philips's Manor. GBC. | AD89: 429 | AE89: 27 | AF89: Book One Part One | AG89: Ann & Elizabeth | AH89: Ben Fowler | AI89: Ship Ann & Elizabeth bound for Port Roseway Ben Fowler, Master
A90: John | B90: Rogers | C90: - | D90: - | E90: - | F90: - | G90: Male | H90: 29 | I90: 1754 | J90: Black | K90: African American | L90: Black | M90: - | N90: - | O90: England | R90: =IFERROR(INDEX(Sheet2!$C:$C, MATCH(P90&Q90, Sheet2!$E:$E, 0)) & ", " & INDEX(Sheet2!$D:$D, MATCH(P90&Q90, Sheet2!$E:$E, 0)), "-") -> - | S90: New York | T90: - | U90: New York | V90: 1783 | W90: Port Roseway | Y90: Canada | Z90: Book of Negroes, British Headquarters Papers PRO 30/55/100; Loyalist evacuation shipping lists (1782–1784) | AA90: Book of Negroes | AB90: John Rogers, 29, stout fellow, (Andrew Gibson). Formerly slave to Captain Rogers, Brig Dispatch, who went to England and left him free. | AD90: 428 | AE90: 27 | AF90: Book One Part One | AG90: Ann & Elizabeth | AH90: Ben Fowler | AI90: Ship Ann & Elizabeth bound for Port Roseway Ben Fowler, Master
A91: Thomas | B91: Edmonds | C91: - | D91: - | E91: - | F91: - | G91: Child Male | H91: 5 | I91: 1778 | J91: Black | K91: African American | L91: Black | M91: - | N91: - | O91: Charlestown | R91: =IFERROR(INDEX(Sheet2!$C:$C, MATCH(P91&Q91, Sheet2!$E:$E, 0)) & ", " & INDEX(Sheet2!$D:$D, MATCH(P91&Q91, Sheet2!$E:$E, 0)), "-") -> - | S91: New York | T91: - | U91: New York | V91: 1783 | W91: Port Roseway | Y91: Canada | Z91: Book of Negroes, British Headquarters Papers PRO 30/55/100; Loyalist evacuation shipping lists (1782–1784) | AA91: Book of Negroes | AB91: Thomas Edmonds, 5, small boy, (Stephen Shakespeare). Formerly slave to Mr. Edmonds, Charlestown; left him 5 years past. | AD91: 427 | AE91: 27 | AF91: Book One Part One | AG91: Ann & Elizabeth | AH91: Ben Fowler | AI91: Ship Ann & Elizabeth bound for Port Roseway Ben Fowler, Master
... A100: John | B100: Dunham | C100: - | D100: - | E100: - | F100: - | G100: Male | H100: 25 | I100: 1758 | J100: Black | K100: African American | L100: Black | M100: - | N100: - | O100: Augusta | R100: =IFERROR(INDEX(Sheet2!$C:$C, MATCH(P100&Q100, Sheet2!$E:$E, 0)) & ", " & INDEX(Sheet2!$D:$D, MATCH(P100&Q100, Sheet2!$E:$E, 0)), "-") -> - | S100: New York | T100: - | U100: New York | V100: 1783 | W100: Port Roseway | Y100: Canada | Z100: Book of Negroes, British Headquarters Papers PRO 30/55/100; Loyalist evacuation shipping lists (1782–1784) | AA100: Book of Negroes | AB100: John Dunham, 25, slender fellow, (Nathaniel Hannah). Formerly slave to James Dunham of Augusta; left him 5 years past. | AD100: 421 | AE100: 27 | AF100: Book One Part One | AG100: Ann & Elizabeth | AH100: Ben Fowler | AI100: Ship Ann & Elizabeth bound for Port Roseway Ben Fowler, Master
A101: Dan | B101: - | G101: Child Male | H101: 7 | I101: 1776 | M101: - | N101: - | O101: - | R101: =IFERROR(INDEX(Sheet2!$C:$C, MATCH(P101&Q101, Sheet2!$E:$E, 0)) & ", " & INDEX(Sheet2!$D:$D, MATCH(P101&Q101, Sheet2!$E:$E, 0)), "-") -> - | S101: New York | U101: New York | V101: 1783 | W101: Bremer Lee | Y101: Canada | Z101: Book of Negroes, British Headquarters Papers PRO 30/55/100; Loyalist evacuation shipping lists (1782–1784) | AA101: Book of Negroes | AD101: 965 | AE101: 41 | AG101: Antelope | AH101: Gordon
A102: George | B102: Bishick | G102: Male | H102: 26 | I102: 1757 | M102: - | N102: - | O102: - | R102: =IFERROR(INDEX(Sheet2!$C:$C, MATCH(P102&Q102, Sheet2!$E:$E, 0)) & ", " & INDEX(Sheet2!$D:$D, MATCH(P102&Q102, Sheet2!$E:$E, 0)), "-") -> - | S102: New York | U102: New York | V102: 1783 | W102: Bremer Lee | Y102: Canada | Z102: Book of Negroes, British Headquarters Papers PRO 30/55/100; Loyalist evacuation shipping lists (1782–1784) | AA102: Book of Negroes | AD102: 966 | AE102: 41 | AG102: Antelope | AH102: Gordon
A103: Dan | B103: - | C103: - | D103: - | E103: - | F103: - | G103: Child Male | H103: 7 | I103: 1776 | J103: Black | K103: African American | L103: Black | M103: East Friesland | N103: - | O103: Oyster Bay | R103: =IFERROR(INDEX(Sheet2!$C:$C, MATCH(P103&Q103, Sheet2!$E:$E, 0)) & ", " & INDEX(Sheet2!$D:$D, MATCH(P103&Q103, Sheet2!$E:$E, 0)), "-") -> - | S103: - | T103: - | U103: - | V103: - | W103: - | Y103: Canada | Z103: - | AA103: - | AB103: Dan, 7, likely boy, Kloproth Lt. Anhalt Zerbel of East Friesland, claimant. (Kloproth). Produces a receipt from John Oakes of Oyster Bay of having bought him for seven guineas, who insures him his property. | AD103: 882 | AE103: - | AF103: Book One Part Two | AG103: Antelope Gordon | AH103: - | AI103: Antelope Gordon bound for Bremer Lee
A104: George | B104: Bishick | C104: - | D104: - | E104: - | F104: - | G104: Male | H104: 26 | I104: 1757 | J104: Black | K104: African American | L104: Black | M104: - | N104: - | O104: Virginia | R104: =IFERROR(INDEX(Sheet2!$C:$C, MATCH(P104&Q104, Sheet2!$E:$E, 0)) & ", " & INDEX(Sheet2!$D:$D, MATCH(P104&Q104, Sheet2!$E:$E, 0)), "-") -> - | S104: - | T104: Virginia | U104: - | V104: - | W104: - | Y104: Canada | Z104: - | AA104: - | AB104: George Bishick, 26, stout fellow. He is Cook on board the ship. Left Virginia 6 years ago. Says he was born free and brought off by a party of marines of the Otter Sloop. | AD104: 883 | AE104: - | AF104: Book One Part Two | AG104: Antelope Gordon | AH104: - | AI104: Antelope Gordon bound for Bremer Lee
A105: Dan | B105: - | C105: - | D105: - | E105: - | F105: - | G105: Child Male | H105: 7 | I105: 1776 | J105: Black | K105: African American | L105: Black | M105: East Friesland | N105: - | O105: Oyster Bay | R105: =IFERROR(INDEX(Sheet2!$C:$C, MATCH(P105&Q105, Sheet2!$E:$E, 0)) & ", " & INDEX(Sheet2!$D:$D, MATCH(P105&Q105, Sheet2!$E:$E, 0)), "-") -> - | S105: - | T105: - | U105: - | V105: - | W105: - | Y105: Canada | Z105: - | AA105: - | AB105: Dan, 7, likely boy, Kloproth Lt. Anhalt Zerbel of East Friesland, claimant. (Kloproth). Produces a receipt from John Oakes of Oyster Bay of having bought him for seven guineas, who insures him his property. | AD105: 1158 | AE105: - | AF105: Book One Part Two | AG105: Antelope Gordon | AH105: - | AI105: Antelope Gordon bound for Bremer Lee
A106: George | B106: Bishick | C106: - | D106: - | E106: - | F106: - | G106: Male | H106: 26 | I106: 1757 | J106: Black | K106: African American | L106: Black | M106: - | N106: - | O106: Virginia | R106: =IFERROR(INDEX(Sheet2!$C:$C, MATCH(P106&Q106, Sheet2!$E:$E, 0)) & ", " & INDEX(Sheet2!$D:$D, MATCH(P106&Q106, Sheet2!$E:$E, 0)), "-") -> - | S106: - | T106: Virginia | U106: - | V106: - | W106: - | Y106: Canada | Z106: - | AA106: - | AB106: George Bishick, 26, stout fellow. He is Cook on board the ship. Left Virginia 6 years ago. Says he was born free and brought off by a party of marines of the Otter Sloop. | AD106: 1159 | AE106: - | AF106: Book One Part Two | AG106: Antelope Gordon | AH106: - | AI106: Antelope Gordon bound for Bremer Lee
A107: James | B107: Jackson | C107: - | D107: - | E107: - | F107: - | G107: Child Male | H107: 12 | I107: 1771 | J107: Black | K107: African American | L107: Black | M107: - | N107: - | O107: Shoemaker | R107: =IFERROR(INDEX(Sheet2!$C:$C, MATCH(P107&Q107, Sheet2!$E:$E, 0)) & ", " & INDEX(Sheet2!$D:$D, MATCH(P107&Q107, Sheet2!$E:$E, 0)), "-") -> - | S107: New York | T107: - | U107: New York | V107: 8 Jun 1783 | W107: Port Roseway | Y107: Canada | Z107: Book of Negroes, British Headquarters Papers PRO 30/55/100; Loyalist evacuation shipping lists (1782–1784) | AA107: Loyalist evacuation lists | AB107: James Jackson, 12, stout boy, (Edward Green). Produced a Certificate from Benjamin James that he is free, both indented to Edward Green till they are 21 to learn the trade of Shoemaker. | AD107: 823 | AE107: 30 | AF107: Book One Part One | AG107: Apollo | AH107: John Adamson | AI107: Apollo bound for Port Roseway John Adamson
A108: Bob | B108: - | C108: - | D108: - | E108: - | F108: - | G108: Child Male | H108: 15 | I108: 1768 | J108: Black | K108: African American | L108: Black | M108: - | N108: - | O108: - | R108: =IFERROR(INDEX(Sheet2!$C:$C, MATCH(P108&Q108, Sheet2!$E:$E, 0)) & ", " & INDEX(Sheet2!$D:$D, MATCH(P108&Q108, Sheet2!$E:$E, 0)), "-") -> - | S108: - | T108: - | U108: - | V108: - | W108: St. John's | Y108: Canada | Z108: - | AA108: - | AB108: Bob, 15, likely boy, (Adj. Cunningham. His property. | AD108: 1969 | AE108: - | AF108: Book One Part Two | AG108: Apollo | AH108: - | AI108: Apollo bound for St. John's
A109: Jupiter | B109: Wise | C109: - | D109: - | E109: - | F109: - | G109: Male | H109: 25 | I109: 1758 | J109: Black | K109: African American | L109: Black | M109: - | N109: - | O109: - | R109: =IFERROR(INDEX(Sheet2!$C:$C, MATCH(P109&Q109, Sheet2!$E:$E, 0)) & ", " & INDEX(Sheet2!$D:$D, MATCH(P109&Q109, Sheet2!$E:$E, 0)), "-") -> - | S109: - | T109: - | U109: - | V109: - | W109: Port Roseway | Y109: Canada | Z109: - | AA109: - | AB109: Jupiter Wise, 25, stout fellow, B, (Henry Hotchinson). Certified to be free by the Commandant. | AD109: 774 | AE109: - | AF109: Book One Part One | AG109: Apollo | AH109: John Adamson | AI109: Apollo bound for Port Roseway John Adamson
A110: Jeff | B110: - | C110: - | D110: - | E110: - | F110: - | G110: Child Male | H110: 12 | I110: 1771 | J110: Black | K110: African American | L110: Black | M110: - | N110: - | O110: - | R110: =IFERROR(INDEX(Sheet2!$C:$C, MATCH(P110&Q110, Sheet2!$E:$E, 0)) & ", " & INDEX(Sheet2!$D:$D, MATCH(P110&Q110, Sheet2!$E:$E, 0)), "-") -> - | S110: - | T110: - | U110: - | V110: - | W110: St. John's | Y110: Canada | Z110: - | AA110: - | AB110: Jeff, 12, likely boy, (Lieut. B. Ward). His own property. | AD110: 1970 | AE110: - | AF110: Book One Part Two | AG110: Apollo | AH110: - | AI110: Apollo bound for St. John's
A111: Vinia | B111: - | C111: - | D111: - | E111: - | F111: - | G111: Female | H111: 25 | I111: 1758 | J111: Black | K111: African American | L111: Black | M111: - | N111: - | O111: - | R111: =IFERROR(INDEX(Sheet2!$C:$C, MATCH(P111&Q111, Sheet2!$E:$E, 0)) & ", " & INDEX(Sheet2!$D:$D, MATCH(P111&Q111, Sheet2!$E:$E, 0)), "-") -> - | S111: New York | T111: - | U111: New York | V111: 8 Jun 1783 | W111: St. John's | Y111: Canada | Z111: Book of Negroes, British Headquarters Papers PRO 30/55/100; Loyalist evacuation shipping lists (1782–1784) | AA111: Loyalist evacuation lists | AB111: Vinia, 25, stout wench, M, (Capt. Willmot). Capt. Willmot's property. | AD111: 1971 | AE111: 62 | AF111: Book One Part Two | AG111: Apollo | AH111: - | AI111: Apollo bound for St. John's
A112: Cara | B112: Wilkins | C112: - | D112: - | E112: - | F112: - | G112: Female | H112: 27 | I112: 1756 | J112: Black | K112: African American | L112: Black | M112: - | N112: - | O112: New Jersey | R112: =IFERROR(INDEX(Sheet2!$C:$C, MATCH(P112&Q112, Sheet2!$E:$E, 0)) & ", " & INDEX(Sheet2!$D:$D, MATCH(P112&Q112, Sheet2!$E:$E, 0)), "-") -> - | S112: Formerly slave to John Wilkinson | T112: New Jersey | U112: - | V112: - | W112: Port Roseway | Y112: Canada | Z112: - | AA112: - | AB112: Cara Wilkins, 27, stout wench, M, (Lewis Palmer). Formerly slave to John Wilkinson, New Jersey; left him in the year 1776. | AD112: 773 | AE112: - | AF112: Book One Part One | AG112: Apollo | AH112: John Adamson | AI112: Apollo bound for Port Roseway John Adamson
A113: Edward | B113: Jackson | C113: - | D113: - | E113: - | F113: - | G113: Child Male | H113: 14 | I113: 1769 | J113: Black | K113: African American | L113: Black | M113: - | N113: - | O113: - | R113: =IFERROR(INDEX(Sheet2!$C:$C, MATCH(P113&Q113, Sheet2!$E:$E, 0)) & ", " & INDEX(Sheet2!$D:$D, MATCH(P113&Q113, Sheet2!$E:$E, 0)), "-") -> - | S113: New York | T113: - | U113: New York | V113: 8 Jun 1783 | W113: Port Roseway | Y113: Canada | Z113: Book of Negroes, British Headquarters Papers PRO 30/55/100; Loyalist evacuation shipping lists (1782–1784) | AA113: Loyalist evacuation lists | AB113: Edward Jackson, 14, stout boy, (Edward Green). Produced a Certificate from Benjamin James that he is free. | AD113: 822 | AE113: 39 | AF113: Book One Part One | AG113: Apollo | AH113: John Adamson | AI113: Apollo bound for Port Roseway John Adamson
A114: Dinah | B114: - | C114: - | D114: - | E114: - | F114: - | G114: Female | H114: 26 | I114: 1757 | J114: Black | K114: African American | L114: Black | M114: Dinah | N114: - | O114: Port Roseway | R114: =IFERROR(INDEX(Sheet2!$C:$C, MATCH(P114&Q114, Sheet2!$E:$E, 0)) & ", " & INDEX(Sheet2!$D:$D, MATCH(P114&Q114, Sheet2!$E:$E, 0)), "-") -> - | S114: New York | T114: - | U114: New York | V114: 8 Jun 1783 | W114: Port Roseway | Y114: Canada | Z114: Book of Negroes, British Headquarters Papers PRO 30/55/100; Loyalist evacuation shipping lists (1782–1784) | AA114: Loyalist evacuation lists | AB114: Dinah, 26, stout wench, M. Robert Wilkins of Port Roseway, claimant. (Robert Wilkins). His property having produced a Bill of Sale. | AD114: 825 | AE114: 39 | AF114: Book One Part One | AG114: Apollo | AH114: John Adamson | AI114: Apollo bound for Port Roseway John Adamson
A115: Sally | B115: Bowden | C115: - | D115: - | E115: - | F115: - | G115: Female | H115: 27 | I115: 1756 | J115: Black | K115: African American | L115: Black | M115: - | N115: - | O115: - | R115: =IFERROR(INDEX(Sheet2!$C:$C, MATCH(P115&Q115, Sheet2!$E:$E, 0)) & ", " & INDEX(Sheet2!$D:$D, MATCH(P115&Q115, Sheet2!$E:$E, 0)), "-") -> - | S115: - | T115: - | U115: - | V115: - | W115: Port Roseway | Y115: Canada | Z115: - | AA115: - | AB115: Sally Bowden, 27, ordinary wench, B. | AD115: 776 | AE115: - | AF115: Book One Part One | AG115: Apollo | AH115: John Adamson | AI115: Apollo bound for Port Roseway John Adamson
A116: Roger their | B116: son | G116: Child Male | H116: 14 | I116: 1769 | M116: - | N116: - | O116: - | R116: =IFERROR(INDEX(Sheet2!$C:$C, MATCH(P116&Q116, Sheet2!$E:$E, 0)) & ", " & INDEX(Sheet2!$D:$D, MATCH(P116&Q116, Sheet2!$E:$E, 0)), "-") -> - | S116: New York | U116: New York | V116: 8 Jun 1783 | W116: Port Roseway | Y116: Canada | Z116: Book of Negroes, British Headquarters Papers PRO 30/55/100; Loyalist evacuation shipping lists (1782–1784) | AA116: Loyalist evacuation lists | AD116: 598 | AE116: 30 | AG116: Apollo | AH116: John Adams
A117: Freelove his | B117: wife | G117: Female | H117: 49 | I117: 1734 | M117: - | N117: - | O117: - | R117: =IFERROR(INDEX(Sheet2!$C:$C, MATCH(P117&Q117, Sheet2!$E:$E, 0)) & ", " & INDEX(Sheet2!$D:$D, MATCH(P117&Q117, Sheet2!$E:$E, 0)), "-") -> - | S117: New York | U117: New York | V117: 8 Jun 1783 | W117: Port Roseway | Y117: Canada | Z117: Book of Negroes, British Headquarters Papers PRO 30/55/100; Loyalist evacuation shipping lists (1782–1784) | AA117: Loyalist evacuation lists | AD117: 597 | AE117: 30 | AG117: Apollo | AH117: John Adams
A118: Thomas | B118: Rogers | C118: - | D118: - | E118: - | F118: - | G118: Male | H118: 40 | I118: 1743 | J118: Black | K118: African American | L118: Black | M118: Chester County | N118: - | O118: Pennsylvania | R118: =IFERROR(INDEX(Sheet2!$C:$C, MATCH(P118&Q118, Sheet2!$E:$E, 0)) & ", " & INDEX(Sheet2!$D:$D, MATCH(P118&Q118, Sheet2!$E:$E, 0)), "-") -> - | S118: Chester County | T118: Pennsylvania | U118: - | V118: - | W118: Port Roseway | Y118: Canada | Z118: - | AA118: - | AB118: Thomas Rogers, 40, ordinary fellow, B, (Lewis Palmer). Formerly slave to Thomas Wollerd, Chester County, Pennsylvania; left him about 5 years ago. | AD118: 772 | AE118: - | AF118: Book One Part One | AG118: Apollo | AH118: John Adamson | AI118: Apollo bound for Port Roseway John Adamson
A119: Robert | G119: Male | I119: - | J119: Black | K119: African American | L119: Black | M119: - | N119: - | O119: - | R119: =IFERROR(INDEX(Sheet2!$C:$C, MATCH(P119&Q119, Sheet2!$E:$E, 0)) & ", " & INDEX(Sheet2!$D:$D, MATCH(P119&Q119, Sheet2!$E:$E, 0)), "-") -> - | W119: St. John's | Y119: Canada | AB119: Robert, her Vinia's infant, (Capt. Willmot). Capt Willmot's property. | AD119: 2720 | AF119: Book One Part Two | AG119: Apollo | AH119: - | AI119: Apollo bound for St. John's
A120: Harry | G120: Male | I120: - | J120: Black | K120: African American | L120: Black | M120: - | N120: - | O120: - | R120: =IFERROR(INDEX(Sheet2!$C:$C, MATCH(P120&Q120, Sheet2!$E:$E, 0)) & ", " & INDEX(Sheet2!$D:$D, MATCH(P120&Q120, Sheet2!$E:$E, 0)), "-") -> - | W120: St. John's | Y120: Canada | AB120: Harry, her Vinia's infant, (Capt. Willmot). Capt. Willmot's property. | AD120: 2719 | AF120: Book One Part Two | AG120: Apollo | AH120: - | AI120: Apollo bound for St. John's
A121: Jack | B121: Rogers | G121: Male | H121: 50 | I121: 1733 | J121: Black | K121: African American | L121: Black | M121: Newport | N121: - | O121: Rhode Island | R121: =IFERROR(INDEX(Sheet2!$C:$C, MATCH(P121&Q121, Sheet2!$E:$E, 0)) & ", " & INDEX(Sheet2!$D:$D, MATCH(P121&Q121, Sheet2!$E:$E, 0)), "-") -> - | W121: Port Roseway | Y121: Canada | AB121: Jack Rogers, 50, stout man, (John Libby). Left free by his master, James Rogers, Newport, Rhode Island, who died 5 years before the war. | AD121: 2696 | AF121: Book One Part One | AG121: Apollo | AH121: John Adams | AI121: Ship Apollo bound for Port Roseway John Adams
A122: Dempsey | B122: Bowden | C122: - | D122: - | E122: - | F122: - | G122: Child Male | H122: 2 | I122: 1781 | J122: Black | K122: African American | L122: Black | M122: - | N122: - | O122: - | R122: =IFERROR(INDEX(Sheet2!$C:$C, MATCH(P122&Q122, Sheet2!$E:$E, 0)) & ", " & INDEX(Sheet2!$D:$D, MATCH(P122&Q122, Sheet2!$E:$E, 0)), "-") -> - | S122: - | T122: - | U122: - | V122: - | W122: Port Roseway | Y122: Canada | Z122: - | AA122: - | AB122: Dempsey Bowden, 2 months, M. | AD122: 777 | AE122: - | AF122: Book One Part One | AG122: Apollo | AH122: John Adamson | AI122: Apollo bound for Port Roseway John Adamson
A123: Silvia his | B123: wife | G123: Female | H123: 36 | I123: 1747 | M123: - | N123: - | O123: - | R123: =IFERROR(INDEX(Sheet2!$C:$C, MATCH(P123&Q123, Sheet2!$E:$E, 0)) & ", " & INDEX(Sheet2!$D:$D, MATCH(P123&Q123, Sheet2!$E:$E, 0)), "-") -> - | S123: New York | U123: New York | V123: 8 Jun 1783 | W123: Port Roseway | Y123: Canada | Z123: Book of Negroes, British Headquarters Papers PRO 30/55/100; Loyalist evacuation shipping lists (1782–1784) | AA123: Loyalist evacuation lists | AD123: 602 | AE123: 30 | AG123: Apollo | AH123: John Adams
A124: Henry | B124: Carter | C124: - | D124: - | E124: - | F124: - | G124: Male | H124: 24 | I124: 1759 | J124: Black | K124: African American | L124: Black | M124: Middlesex | N124: - | O124: Virginia | R124: =IFERROR(INDEX(Sheet2!$C:$C, MATCH(P124&Q124, Sheet2!$E:$E, 0)) & ", " & INDEX(Sheet2!$D:$D, MATCH(P124&Q124, Sheet2!$E:$E, 0)), "-") -> - | S124: New York | T124: Virginia | U124: New York | V124: 8 Jun 1783 | W124: Port Roseway | Y124: Canada | Z124: Book of Negroes, British Headquarters Papers PRO 30/55/100; Loyalist evacuation shipping lists (1782–1784) | AA124: Loyalist evacuation lists | AB124: Henry Carter, 24, stout fellow, (Edward Green). Formerly slave to William Elliot of Middlesex, Virginia; left him 3 years ago. GBC. | AD124: 824 | AE124: 39 | AF124: Book One Part One | AG124: Apollo | AH124: John Adamson | AI124: Apollo bound for Port Roseway John Adamson
A125: Sealia | B125: Bowden | C125: - | D125: - | E125: - | F125: - | G125: Female | H125: 27 | I125: 1756 | J125: Black | K125: African American | L125: Black | M125: Norfolk | N125: - | O125: Virginia | R125: =IFERROR(INDEX(Sheet2!$C:$C, MATCH(P125&Q125, Sheet2!$E:$E, 0)) & ", " & INDEX(Sheet2!$D:$D, MATCH(P125&Q125, Sheet2!$E:$E, 0)), "-") -> - | S125: Norfolk | T125: Virginia | U125: - | V125: - | W125: Port Roseway | Y125: Canada | Z125: - | AA125: - | AB125: Sealia Bowden, 27, ordinary wench, M, (Atkinson). Formerly slave to Solomon Dean, Norfolk, Virginia; left him in the year 1776. GBC. | AD125: 775 | AE125: - | AF125: Book One Part One | AG125: Apollo | AH125: John Adamson | AI125: Apollo bound for Port Roseway John Adamson
A126: Nathaniel | B126: Black | C126: - | D126: - | E126: - | F126: - | G126: Child Male | H126: 1½ | I126: - | J126: Black | K126: African American | L126: Black | M126: - | N126: - | O126: - | R126: =IFERROR(INDEX(Sheet2!$C:$C, MATCH(P126&Q126, Sheet2!$E:$E, 0)) & ", " & INDEX(Sheet2!$D:$D, MATCH(P126&Q126, Sheet2!$E:$E, 0)), "-") -> - | S126: New York | T126: - | U126: New York | V126: 8 Jun 1783 | W126: Port Roseway | Y126: Canada | Z126: Book of Negroes, British Headquarters Papers PRO 30/55/100; Loyalist evacuation shipping lists (1782–1784) | AA126: Loyalist evacuation lists | AB126: Nathaniel Black, 1½ , (Capt. Lounz). | AD126: 285 | AE126: 24 | AF126: Book One Part One | AG126: Apollo | AH126: John adamson | AI126: Ship Apollo bound for Port Roseway John adamson, Master
A127: St | B127: Louis | C127: - | D127: - | E127: - | F127: - | G127: Male | H127: 60 | I127: 1723 | J127: Black | K127: African American | L127: Black | M127: - | N127: - | O127: St. Louis | R127: =IFERROR(INDEX(Sheet2!$C:$C, MATCH(P127&Q127, Sheet2!$E:$E, 0)) & ", " & INDEX(Sheet2!$D:$D, MATCH(P127&Q127, Sheet2!$E:$E, 0)), "-") -> - | S127: New York | T127: - | U127: New York | V127: 8 Jun 1783 | W127: Port Roseway | Y127: Canada | Z127: Book of Negroes, British Headquarters Papers PRO 30/55/100; Loyalist evacuation shipping lists (1782–1784) | AA127: Loyalist evacuation lists | AB127: St. Louis, 60, thin, (John Libby). French free Negro. | AD127: 544 | AE127: 30 | AF127: Book One Part One | AG127: Apollo | AH127: John Adams | AI127: Ship Apollo bound for Port Roseway John Adams
A128: Jacob | B128: Wigfall | C128: - | D128: - | E128: - | F128: - | G128: Male | H128: 36 | I128: 1747 | J128: Black | K128: African American | L128: Black | M128: Charlestown | N128: - | O128: South Carolina | R128: =IFERROR(INDEX(Sheet2!$C:$C, MATCH(P128&Q128, Sheet2!$E:$E, 0)) & ", " & INDEX(Sheet2!$D:$D, MATCH(P128&Q128, Sheet2!$E:$E, 0)), "-") -> - | S128: New York | T128: South Carolina | U128: New York | V128: 8 Jun 1783 | W128: Port Roseway | Y128: Canada | Z128: Book of Negroes, British Headquarters Papers PRO 30/55/100; Loyalist evacuation shipping lists (1782–1784) | AA128: Loyalist evacuation lists | AB128: Jacob Wigfall, 36, thin (Richard Wheaton). Formerly the property of Mr. Joseph Wigfall, Charlestown, South Carolina; left him in the year 1779. GBCP | AD128: 545 | AE128: 30 | AF128: Book One Part One | AG128: Apollo | AH128: John Adams | AI128: Ship Apollo bound for Port Roseway John Adams
A129: Silvia | B129: his wife | C129: - | D129: - | E129: - | F129: - | G129: Female | H129: 36 | I129: 1747 | J129: Black | K129: African American | L129: Black | M129: Charlestown | N129: - | O129: South Carolina | R129: =IFERROR(INDEX(Sheet2!$C:$C, MATCH(P129&Q129, Sheet2!$E:$E, 0)) & ", " & INDEX(Sheet2!$D:$D, MATCH(P129&Q129, Sheet2!$E:$E, 0)), "-") -> - | S129: New York | T129: South Carolina | U129: New York | V129: 8 Jun 1783 | W129: Port Roseway | Y129: Canada | Z129: Book of Negroes, British Headquarters Papers PRO 30/55/100; Loyalist evacuation shipping lists (1782–1784) | AA129: Loyalist evacuation lists | AB129: Silvia his wife, 36, stout squat wench, (Richard Wheaton). Formerly the property of Mr. Joseph Wigfall, Charlestown, South Carolina; left him in the year 1779. GBCP | AD129: 546 | AE129: 30 | AF129: Book One Part One | AG129: Apollo | AH129: John Adams | AI129: Ship Apollo bound for Port Roseway John Adams
A130: Ismael | B130: Warren | C130: - | D130: - | E130: - | F130: - | G130: Male | H130: 25 | I130: 1758 | J130: Black | K130: African American | L130: Black | M130: Charlestown | N130: - | O130: South Carolina | R130: =IFERROR(INDEX(Sheet2!$C:$C, MATCH(P130&Q130, Sheet2!$E:$E, 0)) & ", " & INDEX(Sheet2!$D:$D, MATCH(P130&Q130, Sheet2!$E:$E, 0)), "-") -> - | S130: Charlestown | T130: South Carolina | U130: - | V130: - | W130: Port Roseway | Y130: Canada | Z130: - | AA130: - | AB130: Ismael Warren , 25, stout fellow, (William Campbell). Formerly slave to Joseph Warren, Charlestown, South Carolina; left him in the year 1779. GBCP | AD130: 547 | AE130: - | AF130: Book One Part One | AG130: Apollo | AH130: John Adams | AI130: Ship Apollo bound for Port Roseway John Adams
A131: Effy | B131: Black | C131: - | D131: - | E131: - | F131: - | G131: Female | H131: 25 | I131: 1758 | J131: Black | K131: African American | L131: Black | M131: - | N131: - | O131: - | R131: =IFERROR(INDEX(Sheet2!$C:$C, MATCH(P131&Q131, Sheet2!$E:$E, 0)) & ", " & INDEX(Sheet2!$D:$D, MATCH(P131&Q131, Sheet2!$E:$E, 0)), "-") -> - | S131: New York | T131: - | U131: New York | V131: 8 Jun 1783 | W131: Port Roseway | Y131: Canada | Z131: Book of Negroes, British Headquarters Papers PRO 30/55/100; Loyalist evacuation shipping lists (1782–1784) | AA131: Loyalist evacuation lists | AB131: Effy Black, 25, stout wench, (Capt. Lounz). Formerly slave to John Nesbit, Strasburg ferry, Charlestown; left him 5 years past. GBC. | AD131: 284 | AE131: 24 | AF131: Book One Part One | AG131: Apollo | AH131: John adamson | AI131: Ship Apollo bound for Port Roseway John adamson, Master
A132: Nathaniel | B132: Black | C132: - | D132: - | E132: - | F132: - | G132: Male | H132: 50 | I132: 1733 | J132: Black | K132: African American | L132: Black | M132: - | N132: - | O132: - | R132: =IFERROR(INDEX(Sheet2!$C:$C, MATCH(P132&Q132, Sheet2!$E:$E, 0)) & ", " & INDEX(Sheet2!$D:$D, MATCH(P132&Q132, Sheet2!$E:$E, 0)), "-") -> - | S132: New York | T132: - | U132: New York | V132: 8 Jun 1783 | W132: Port Roseway | Y132: Canada | Z132: Book of Negroes, British Headquarters Papers PRO 30/55/100; Loyalist evacuation shipping lists (1782–1784) | AA132: Loyalist evacuation lists | AB132: Nathaniel Black, 50, ordinary fellow, (Capt. Lounz). Formerly slave to John Nesbit, Strasburg ferry, Charlestown; left him 5 years past. GBC. | AD132: 283 | AE132: 24 | AF132: Book One Part One | AG132: Apollo | AH132: John adamson | AI132: Ship Apollo bound for Port Roseway John adamson, Master
...

Sheet Sheet2
A1: County | B1: State | C1: lat | D1: lng | E1: LookupKey
A2: Aleutians East | B2: AK | C2: 55.3669 | D2: -161.9805 | E2: AKAleutians East
A3: Aleutians West | B3: AK | C3: 52.7985 | D3: -106.5633 | E3: AKAleutians West
A4: Anchorage | B4: AK | C4: 61.1498 | D4: -149.1082 | E4: AKAnchorage
A5: Bethel | B5: AK | C5: 60.9132 | D5: -159.8186 | E5: AKBethel
A6: Bristol Bay | B6: AK | C6: 58.7431 | D6: -156.7015 | E6: AKBristol Bay
A7: Chugach | B7: AK | C7: 60.7233 | D7: -145.7583 | E7: AKChugach
A8: Copper River | B8: AK | C8: 61.8855 | D8: -143.97 | E8: AKCopper River
A9: Denali | B9: AK | C9: 63.6714 | D9: -150.0118 | E9: AKDenali
A10: Dillingham | B10: AK | C10: 59.8003 | D10: -158.2346 | E10: AKDillingham
A11: Fairbanks North Star | B11: AK | C11: 64.8078 | D11: -146.5654 | E11: AKFairbanks North Star
A12: Haines | B12: AK | C12: 59.1186 | D12: -135.5007 | E12: AKHaines
A13: Hoonah-Angoon | B13: AK | C13: 58.287 | D13: -135.6393 | E13: AKHoonah-Angoon
... A3145: Weston | B3145: WY | C3145: 43.8404 | D3145: -104.5677 | E3145: WYWeston
